Workbook

Sheet 說明
A1: 美股觀察名單 — 全體成分股「營收 / 營利」對照表 R1.00
A2: 編製時間 2026-09-07 10:18 HKT ｜ 532 隻 ｜ 涵蓋 Sub-Sector Watchlist R4.00（491 隻）與 AI Sector Watchlist R5.00（111 隻），70 隻兩表重疊
A4: 【本表用途】
A5: • 兩份資金流向報告只看價量，唔睇基本面。本表補上每隻成分股嘅「賺唔賺到錢」——最近五個季度營收、四個季度營業利益、
A6: 以及最新一季嘅毛利率／營業利益率／淨利率，令「資金流入邊個板塊」可以同「邊個板塊真係有盈利」對照睇。
A8: 【版面沿用 AI_Growth_Breakeven_Watchlist_R7.xlsx】
A9: • 同樣係「說明 / 主表 / 分級彙總 / 圖表連結 / 資料來源」結構；主表凍結窗格、開篩選、營收欄淺藍底、營利欄淺紅底、級別欄按等級上色。
A10: • 同樣將營收寫成純數字（單位「百萬」寫喺表頭），可直接排序、計算按季變動、畫圖；幣別與季度對照獨立成欄。
A11: • 不同之處（因為資料來源唔同，必須講清楚）：
A12: R7 嘅「淨利｜經常｜一次」三行拆解、「一次性項目清單」、「經常性軌跡」係逐間公司人手查財報寫出嚟嘅。
A13: 本表 532 隻全部由 Yahoo Finance 財報 API 自動抓取，冇人手核實每間公司嘅一次性項目，所以唔會憑空寫呢三欄。
A14: 取而代之，本表用「營業利益」(Operating Income) 作為經常性盈利嘅代理 —— 佢本身已剔除大部分投資收益、
... A49: • 本表為公開資料整理與研究參考，非投資建議。

Sheet 觀察名單
A1: # | B1: 美股 Ticker (按=開圖) | C1: 子板塊 SubSector (R4.00) | D1: 公司 | E1: AI 小群組 (R5.00) ／行業 | F1: 幣別 | G1: 季度對照 (Q-4 → Q0) | H1: 營收 Q-4 (百萬) | I1: 營收 Q-3 (百萬) | J1: 營收 Q-2 (百萬) | K1: 營收 Q-1 (百萬) | L1: 營收 Q0 最新 (百萬) | M1: 營收按年 % (Q0/Q-4) | N1: 營業利益 Q-3 (百萬) | O1: 營業利益 Q-2 (百萬) | P1: 營業利益 Q-1 (百萬) | Q1: 營業利益 Q0 (百萬) | R1: 營業利益率 Q0 % | S1: 毛利 Q0 (百萬) | T1: 毛利率 Q0 % | U1: 淨利 Q0 (百萬) | V1: 淨利率 Q0 % | W1: 年度營收 (最近財年, 百萬) | X1: 年度營業利益 (最近財年, 百萬) | Y1: 年度營業 利益率 % | Z1: 盈利狀態 | AA1: 級 | AB1: 資料截至
A2: 1 | B2: A | C2: 診斷與生命科學工具 | D2: Agilent Technologies, Inc. | E2: Diagnostics & Research | F2: USD | G2: 25Q3 / 25Q4 / 26Q1 / 26Q2 / 26Q3 | H2: 1738 | I2: 1861 | J2: 1798 | K2: 1835 | L2: 1878 | M2: =IF(OR(N(H2)=0,L2=""),"",L2/H2-1) -> 0.080552359 | N2: 443 | O2: 353 | P2: 399 | Q2: 444 | R2: =IF(OR(N(L2)=0,Q2=""),"",Q2/L2) -> 0.23642173 | S2: 1042 | T2: =IF(OR(N(L2)=0,S2=""),"",S2/L2) -> 0.55484558 | U2: 362 | V2: =IF(OR(N(L2)=0,U2=""),"",U2/L2) -> 0.19275825 | W2: 6948 | X2: 1479 | Y2: =IF(OR(N(W2)=0,X2=""),"",X2/W2) -> 0.21286701 | Z2: =IF(AA2="A","四季持續盈利",IF(AA2="B","最新季為正/波動",IF(AA2="C","虧損收窄",IF(AA2="D","虧損擴大或轉虧","數據不足")))) -> 四季持續盈利 | AA2: =IF(COUNT(N2:Q2)<4,"—",IF(MIN(N2:Q2)>0,"A",IF(Q2>0,"B",IF(Q2>N2,"C","D")))) -> A | AB2: 2026-07-31
A3: 2 | B3: AA | C3: 鋁業 | D3: Alcoa Corporation | E3: Aluminum | F3: USD | G3: 25Q2 / 25Q3 / 25Q4 / 26Q1 / 26Q2 | H3: 3018 | I3: 2995 | J3: 3449 | K3: 3193 | L3: 3966 | M3: =IF(OR(N(H3)=0,L3=""),"",L3/H3-1) -> 0.31411531 | N3: 51 | O3: -112 | P3: 426 | Q3: 714 | R3: =IF(OR(N(L3)=0,Q3=""),"",Q3/L3) -> 0.18003026 | S3: 999 | T3: =IF(OR(N(L3)=0,S3=""),"",S3/L3) -> 0.25189107 | U3: 407 | V3: =IF(OR(N(L3)=0,U3=""),"",U3/L3) -> 0.10262229 | W3: 12831 | X3: 758 | Y3: =IF(OR(N(W3)=0,X3=""),"",X3/W3) -> 0.059075676 | Z3: =IF(AA3="A","四季持續盈利",IF(AA3="B","最新季為正/波動",IF(AA3="C","虧損收窄",IF(AA3="D","虧損擴大或轉虧","數據不足")))) -> 最新季為正/波動 | AA3: =IF(COUNT(N3:Q3)<4,"—",IF(MIN(N3:Q3)>0,"A",IF(Q3>0,"B",IF(Q3>N3,"C","D")))) -> B | AB3: 2026-06-30
A4: 3 | B4: AAL | C4: 航空公司 | D4: American Airlines Group Inc. | E4: Airlines | F4: USD | G4: 25Q2 / 25Q3 / 25Q4 / 26Q1 / 26Q2 | H4: 14392 | I4: 13691 | J4: 13999 | K4: 13912 | L4: 16735 | M4: =IF(OR(N(H4)=0,L4=""),"",L4/H4-1) -> 0.16279878 | N4: 158 | O4: 486 | P4: -27 | Q4: 453 | R4: =IF(OR(N(L4)=0,Q4=""),"",Q4/L4) -> 0.027069017 | S4: 2991 | T4: =IF(OR(N(L4)=0,S4=""),"",S4/L4) -> 0.17872722 | U4: 71 | V4: =IF(OR(N(L4)=0,U4=""),"",U4/L4) -> 0.0042426053 | W4: 54633 | X4: 1626 | Y4: =IF(OR(N(W4)=0,X4=""),"",X4/W4) -> 0.029762232 | Z4: =IF(AA4="A","四季持續盈利",IF(AA4="B","最新季為正/波動",IF(AA4="C","虧損收窄",IF(AA4="D","虧損擴大或轉虧","數據不足")))) -> 最新季為正/波動 | AA4: =IF(COUNT(N4:Q4)<4,"—",IF(MIN(N4:Q4)>0,"A",IF(Q4>0,"B",IF(Q4>N4,"C","D")))) -> B | AB4: 2026-06-30
A5: 4 | B5: AAOI | C5: 光通訊/CPO | D5: Applied Optoelectronics, Inc. | E5: Communication Equipment | F5: USD | G5: 25Q2 / 25Q3 / 25Q4 / 26Q1 / 26Q2 | H5: 102.952 | I5: 118.63 | J5: 134.274 | K5: 151.144 | L5: 191.922 | M5: =IF(OR(N(H5)=0,L5=""),"",L5/H5-1) -> 0.86418914 | N5: -14.968 | O5: -11.352 | P5: -12.877 | Q5: -23.847 | R5: =IF(OR(N(L5)=0,Q5=""),"",Q5/L5) -> -0.1242536 | S5: 53.207 | T5: =IF(OR(N(L5)=0,S5=""),"",S5/L5) -> 0.27723242 | U5: -22.781 | V5: =IF(OR(N(L5)=0,U5=""),"",U5/L5) -> -0.11869926 | W5: 455.715 | X5: -49.736 | Y5: =IF(OR(N(W5)=0,X5=""),"",X5/W5) -> -0.10913839 | Z5: =IF(AA5="A","四季持續盈利",IF(AA5="B","最新季為正/波動",IF(AA5="C","虧損收窄",IF(AA5="D","虧損擴大或轉虧","數據不足")))) -> 虧損擴大或轉虧 | AA5: =IF(COUNT(N5:Q5)<4,"—",IF(MIN(N5:Q5)>0,"A",IF(Q5>0,"B",IF(Q5>N5,"C","D")))) -> D | AB5: 2026-06-30
A6: 5 | B6: AAON | C6: 樓宇產品與HVAC | D6: AAON, Inc. | E6: Building Products & Equipment | F6: USD | G6: 25Q2 / 25Q3 / 25Q4 / 26Q1 / 26Q2 | H6: 311.567 | I6: 384.238 | J6: 424.217 | K6: 496.936 | L6: 626.976 | M6: =IF(OR(N(H6)=0,L6=""),"",L6/H6-1) -> 1.0123312 | N6: 43.631 | O6: 43.96 | P6: 57.059 | Q6: 70.332 | R6: =IF(OR(N(L6)=0,Q6=""),"",Q6/L6) -> 0.11217654 | S6: 152.491 | T6: =IF(OR(N(L6)=0,S6=""),"",S6/L6) -> 0.24321665 | U6: 56.659 | V6: =IF(OR(N(L6)=0,U6=""),"",U6/L6) -> 0.09036869 | W6: 1442.076 | X6: 152.349 | Y6: =IF(OR(N(W6)=0,X6=""),"",X6/W6) -> 0.10564561 | Z6: =IF(AA6="A","四季持續盈利",IF(AA6="B","最新季為正/波動",IF(AA6="C","虧損收窄",IF(AA6="D","虧損擴大或轉虧","數據不足")))) -> 四季持續盈利 | AA6: =IF(COUNT(N6:Q6)<4,"—",IF(MIN(N6:Q6)>0,"A",IF(Q6>0,"B",IF(Q6>N6,"C","D")))) -> A | AB6: 2026-06-30
A7: 6 | B7: AAPL | C7: 電子硬件與EMS/連接器 | D7: Apple Inc. | E7: A4 運算 | F7: USD | G7: 25Q2 / 25Q3 / 25Q4 / 26Q1 / 26Q2 | H7: 94036 | I7: 102466 | J7: 143756 | K7: 111184 | L7: 109417 | M7: =IF(OR(N(H7)=0,L7=""),"",L7/H7-1) -> 0.16356502 | N7: 32427 | O7: 50852 | P7: 35885 | Q7: 35695 | R7: =IF(OR(N(L7)=0,Q7=""),"",Q7/L7) -> 0.32622901 | S7: 54770 | T7: =IF(OR(N(L7)=0,S7=""),"",S7/L7) -> 0.50056207 | U7: 29789 | V7: =IF(OR(N(L7)=0,U7=""),"",U7/L7) -> 0.27225203 | W7: 416161 | X7: 133050 | Y7: =IF(OR(N(W7)=0,X7=""),"",X7/W7) -> 0.319708 | Z7: =IF(AA7="A","四季持續盈利",IF(AA7="B","最新季為正/波動",IF(AA7="C","虧損收窄",IF(AA7="D","虧損擴大或轉虧","數據不足")))) -> 四季持續盈利 | AA7: =IF(COUNT(N7:Q7)<4,"—",IF(MIN(N7:Q7)>0,"A",IF(Q7>0,"B",IF(Q7>N7,"C","D")))) -> A | AB7: 2026-06-30
A8: 7 | B8: ABBV | C8: 大型藥廠 | D8: AbbVie Inc. | E8: Drug Manufacturers - General | F8: USD | G8: 25Q2 / 25Q3 / 25Q4 / 26Q1 / 26Q2 | H8: 15423 | I8: 15776 | J8: 16618 | K8: 15002 | L8: 16990 | M8: =IF(OR(N(H8)=0,L8=""),"",L8/H8-1) -> 0.1016015 | N8: 4584 | O8: 5809 | P8: 4734 | Q8: 6723 | R8: =IF(OR(N(L8)=0,Q8=""),"",Q8/L8) -> 0.39570335 | S8: 12699 | T8: =IF(OR(N(L8)=0,S8=""),"",S8/L8) -> 0.74743967 | U8: 3613 | V8: =IF(OR(N(L8)=0,U8=""),"",U8/L8) -> 0.2126545 | W8: 61160 | X8: 20091 | Y8: =IF(OR(N(W8)=0,X8=""),"",X8/W8) -> 0.32849902 | Z8: =IF(AA8="A","四季持續盈利",IF(AA8="B","最新季為正/波動",IF(AA8="C","虧損收窄",IF(AA8="D","虧損擴大或轉虧","數據不足")))) -> 四季持續盈利 | AA8: =IF(COUNT(N8:Q8)<4,"—",IF(MIN(N8:Q8)>0,"A",IF(Q8>0,"B",IF(Q8>N8,"C","D")))) -> A | AB8: 2026-06-30
A9: 8 | B9: ABT | C9: 醫療器械 | D9: Abbott Laboratories | E9: Medical Devices | F9: USD | G9: 25Q2 / 25Q3 / 25Q4 / 26Q1 / 26Q2 | H9: 11142 | I9: 11369 | J9: 11459 | K9: 11164 | M9: =IF(OR(N(H9)=0,L9=""),"",L9/H9-1) | N9: 2057 | O9: 2251 | P9: 1345 | R9: =IF(OR(N(L9)=0,Q9=""),"",Q9/L9) | T9: =IF(OR(N(L9)=0,S9=""),"",S9/L9) | V9: =IF(OR(N(L9)=0,U9=""),"",U9/L9) | W9: 44328 | X9: 8053 | Y9: =IF(OR(N(W9)=0,X9=""),"",X9/W9) -> 0.18166847 | Z9: =IF(AA9="A","四季持續盈利",IF(AA9="B","最新季為正/波動",IF(AA9="C","虧損收窄",IF(AA9="D","虧損擴大或轉虧","數據不足")))) -> 數據不足 | AA9: =IF(COUNT(N9:Q9)<4,"—",IF(MIN(N9:Q9)>0,"A",IF(Q9>0,"B",IF(Q9>N9,"C","D")))) -> — | AB9: 2026-06-30
A10: 9 | B10: ACI | C10: 大賣場與超巿 | D10: Albertsons Companies, Inc. | E10: Grocery Stores | F10: USD | G10: 25Q2 / 25Q3 / 25Q4 / 26Q1 / 26Q2 | H10: 24880.8 | I10: 18915.8 | J10: 19123.7 | K10: 20252.2 | L10: 24941.6 | M10: =IF(OR(N(H10)=0,L10=""),"",L10/H10-1) -> 0.0024436513 | N10: 299.7 | O10: 488.5 | P10: -490.2 | Q10: 258.9 | R10: =IF(OR(N(L10)=0,Q10=""),"",Q10/L10) -> 0.010380248 | S10: 6638.1 | T10: =IF(OR(N(L10)=0,S10=""),"",S10/L10) -> 0.26614572 | U10: 84.7 | V10: =IF(OR(N(L10)=0,U10=""),"",U10/L10) -> 0.0033959329 | W10: 83172.5 | X10: 715.4 | Y10: =IF(OR(N(W10)=0,X10=""),"",X10/W10) -> 0.0086014007 | Z10: =IF(AA10="A","四季持續盈利",IF(AA10="B","最新季為正/波動",IF(AA10="C","虧損收窄",IF(AA10="D","虧損擴大或轉虧","數據不足")))) -> 最新季為正/波動 | AA10: =IF(COUNT(N10:Q10)<4,"—",IF(MIN(N10:Q10)>0,"A",IF(Q10>0,"B",IF(Q10>N10,"C","D")))) -> B | AB10: 2026-05-31
A11: 10 | B11: ACM | C11: 工程建設/EPC | D11: AECOM | E11: Engineering & Construction | F11: USD | G11: 25Q2 / 25Q3 / 25Q4 / 26Q1 / 26Q2 | H11: 4178.44 | I11: 4175.417 | J11: 3830.834 | K11: 3801.143 | L11: 3586.067 | M11: =IF(OR(N(H11)=0,L11=""),"",L11/H11-1) -> -0.14176894 | N11: 291.425 | O11: 240.151 | P11: 252.199 | Q11: -68.41 | R11: =IF(OR(N(L11)=0,Q11=""),"",Q11/L11) -> -0.01907661 | S11: -34.042 | T11: =IF(OR(N(L11)=0,S11=""),"",S11/L11) -> -0.0094928511 | U11: -86.712 | V11: =IF(OR(N(L11)=0,U11=""),"",U11/L11) -> -0.024180251 | W11: 16139.622 | X11: 1058.864 | Y11: =IF(OR(N(W11)=0,X11=""),"",X11/W11) -> 0.065606493 | Z11: =IF(AA11="A","四季持續盈利",IF(AA11="B","最新季為正/波動",IF(AA11="C","虧損收窄",IF(AA11="D","虧損擴大或轉虧","數據不足")))) -> 虧損擴大或轉虧 | AA11: =IF(COUNT(N11:Q11)<4,"—",IF(MIN(N11:Q11)>0,"A",IF(Q11>0,"B",IF(Q11>N11,"C","D")))) -> D | AB11: 2026-06-30
A12: 11 | B12: ACN | C12: IT服務與系統整合 | D12: Accenture plc | E12: G5 IT | F12: USD | G12: 25Q2 / 25Q3 / 25Q4 / 26Q1 / 26Q2 | H12: 17727.871 | I12: 17596.26 | J12: 18742.125 | K12: 18044.066 | L12: 18718.144 | M12: =IF(OR(N(H12)=0,L12=""),"",L12/H12-1) -> 0.055859669 | N12: 2665.015 | O12: 3181.239 | P12: 2493.547 | Q12: 3175.298 | R12: =IF(OR(N(L12)=0,Q12=""),"",Q12/L12) -> 0.16963744 | S12: 6134.335 | T12: =IF(OR(N(L12)=0,S12=""),"",S12/L12) -> 0.32772133 | U12: 2338.989 | V12: =IF(OR(N(L12)=0,U12=""),"",U12/L12) -> 0.12495838 | W12: 69672.977 | X12: 10840.988 | Y12: =IF(OR(N(W12)=0,X12=""),"",X12/W12) -> 0.15559817 | Z12: =IF(AA12="A","四季持續盈利",IF(AA12="B","最新季為正/波動",IF(AA12="C","虧損收窄",IF(AA12="D","虧損擴大或轉虧","數據不足")))) -> 四季持續盈利 | AA12: =IF(COUNT(N12:Q12)<4,"—",IF(MIN(N12:Q12)>0,"A",IF(Q12>0,"B",IF(Q12>N12,"C","D")))) -> A | AB12: 2026-05-31
A13: 12 | B13: ADBE | C13: 企業軟體/SaaS | D13: Adobe Inc. | E13: G3 AI | F13: USD | G13: 25Q2 / 25Q3 / 25Q4 / 26Q1 / 26Q2 | H13: 5873 | I13: 5988 | J13: 6194 | K13: 6398 | L13: 6618 | M13: =IF(OR(N(H13)=0,L13=""),"",L13/H13-1) -> 0.12685169 | N13: 2173 | O13: 2261 | P13: 2418 | Q13: 2238 | R13: =IF(OR(N(L13)=0,Q13=""),"",Q13/L13) -> 0.33816863 | S13: 5903 | T13: =IF(OR(N(L13)=0,S13=""),"",S13/L13) -> 0.89196132 | U13: 1712 | V13: =IF(OR(N(L13)=0,U13=""),"",U13/L13) -> 0.25868843 | W13: 23769 | X13: 8706 | Y13: =IF(OR(N(W13)=0,X13=""),"",X13/W13) -> 0.3662754 | Z13: =IF(AA13="A","四季持續盈利",IF(AA13="B","最新季為正/波動",IF(AA13="C","虧損收窄",IF(AA13="D","虧損擴大或轉虧","數據不足")))) -> 四季持續盈利 | AA13: =IF(COUNT(N13:Q13)<4,"—",IF(MIN(N13:Q13)>0,"A",IF(Q13>0,"B",IF(Q13>N13,"C","D")))) -> A | AB13: 2026-05-31
A14: 13 | B14: ADI | C14: 類比/功率半導體 | D14: Analog Devices, Inc. | E14: Semiconductors | F14: USD | G14: 25Q3 / 25Q4 / 26Q1 / 26Q2 / 26Q3 | H14: 2880.348 | I14: 3076.117 | J14: 3160.263 | K14: 3623.465 | L14: 4021.899 | M14: =IF(OR(N(H14)=0,L14=""),"",L14/H14-1) -> 0.39632399 | N14: 945.211 | O14: 1045.008 | P14: 1379.68 | Q14: 1588.753 | R14: =IF(OR(N(L14)=0,Q14=""),"",Q14/L14) -> 0.39502558 | S14: 2707.544 | T14: =IF(OR(N(L14)=0,S14=""),"",S14/L14) -> 0.6732004 | U14: 1340.09 | V14: =IF(OR(N(L14)=0,U14=""),"",U14/L14) -> 0.33319832 | W14: 11019.707 | X14: 3002.476 | Y14: =IF(OR(N(W14)=0,X14=""),"",X14/W14) -> 0.27246423 | Z14: =IF(AA14="A","四季持續盈利",IF(AA14="B","最新季為正/波動",IF(AA14="C","虧損收窄",IF(AA14="D","虧損擴大或轉虧","數據不足")))) -> 四季持續盈利 | AA14: =IF(COUNT(N14:Q14)<4,"—",IF(MIN(N14:Q14)>0,"A",IF(Q14>0,"B",IF(Q14>N14,"C","D")))) -> A | AB14: 2026-07-31
A15: 14 | B15: ADM | C15: 農產品與農業投入 | D15: Archer-Daniels-Midland Company | E15: Farm Products | F15: USD | G15: 25Q2 / 25Q3 / 25Q4 / 26Q1 / 26Q2 | H15: 21166 | I15: 20372 | J15: 18556 | K15: 20490 | L15: 22681 | M15: =IF(OR(N(H15)=0,L15=""),"",L15/H15-1) -> 0.071577058 | N15: 397 | O15: 320 | P15: 261 | Q15: 909 | R15: =IF(OR(N(L15)=0,Q15=""),"",Q15/L15) -> 0.040077598 | S15: 1935 | T15: =IF(OR(N(L15)=0,S15=""),"",S15/L15) -> 0.085313699 | U15: 908 | V15: =IF(OR(N(L15)=0,U15=""),"",U15/L15) -> 0.040033508 | W15: 80269 | X15: 1424 | Y15: =IF(OR(N(W15)=0,X15=""),"",X15/W15) -> 0.017740348 | Z15: =IF(AA15="A","四季持續盈利",IF(AA15="B","最新季為正/波動",IF(AA15="C","虧損收窄",IF(AA15="D","虧損擴大或轉虧","數據不足")))) -> 四季持續盈利 | AA15: =IF(COUNT(N15:Q15)<4,"—",IF(MIN(N15:Q15)>0,"A",IF(Q15>0,"B",IF(Q15>N15,"C","D")))) -> A | AB15: 2026-06-30
A16: 15 | B16: ADP | C16: 人力與商業服務 | D16: Automatic Data Processing, Inc. | E16: Software - Application | F16: USD | G16: 25Q2 / 25Q3 / 25Q4 / 26Q1 / 26Q2 | H16: 5126.8 | I16: 5175.2 | J16: 5359.3 | K16: 5939.2 | L16: 5473.8 | M16: =IF(OR(N(H16)=0,L16=""),"",L16/H16-1) -> 0.067683545 | N16: 1332.8 | O16: 1401.5 | P16: 1785.5 | Q16: 1259.1 | R16: =IF(OR(N(L16)=0,Q16=""),"",Q16/L16) -> 0.23002302 | S16: 2511.3 | T16: =IF(OR(N(L16)=0,S16=""),"",S16/L16) -> 0.45878549 | U16: 978.6 | V16: =IF(OR(N(L16)=0,U16=""),"",U16/L16) -> 0.17877891 | W16: 21947.4 | X16: 5779 | Y16: =IF(OR(N(W16)=0,X16=""),"",X16/W16) -> 0.26331137 | Z16: =IF(AA16="A","四季持續盈利",IF(AA16="B","最新季為正/波動",IF(AA16="C","虧損收窄",IF(AA16="D","虧損擴大或轉虧","數據不足")))) -> 四季持續盈利 | AA16: =IF(COUNT(N16:Q16)<4,"—",IF(MIN(N16:Q16)>0,"A",IF(Q16>0,"B",IF(Q16>N16,"C","D")))) -> A | AB16: 2026-06-30
A17: 16 | B17: AEHR | C17: — | D17: Aehr Test Systems, Inc. | E17: B3 先進封裝 | F17: USD | G17: 25Q2 / 25Q3 / 25Q4 / 26Q1 / 26Q2 | H17: 14.089 | I17: 10.969 | J17: 9.884 | K17: 10.313 | L17: 18.835 | M17: =IF(OR(N(H17)=0,L17=""),"",L17/H17-1) -> 0.33685854 | N17: -3.847 | O17: -4.861 | P17: -4.229 | Q17: -1.206 | R17: =IF(OR(N(L17)=0,Q17=""),"",Q17/L17) -> -0.064029732 | S17: 8.019 | T17: =IF(OR(N(L17)=0,S17=""),"",S17/L17) -> 0.42574993 | U17: 1.391 | V17: =IF(OR(N(L17)=0,U17=""),"",U17/L17) -> 0.073851872 | W17: 50.001 | X17: -14.143 | Y17: =IF(OR(N(W17)=0,X17=""),"",X17/W17) -> -0.28285434 | Z17: =IF(AA17="A","四季持續盈利",IF(AA17="B","最新季為正/波動",IF(AA17="C","虧損收窄",IF(AA17="D","虧損擴大或轉虧","數據不足")))) -> 虧損收窄 | AA17: =IF(COUNT(N17:Q17)<4,"—",IF(MIN(N17:Q17)>0,"A",IF(Q17>0,"B",IF(Q17>N17,"C","D")))) -> C | AB17: 2026-05-31
A18: 17 | B18: AEM | C18: 黃金與貴金屬礦 | D18: Agnico Eagle Mines Limited | E18: Gold | F18: USD | G18: 25Q2 / 25Q3 / 25Q4 / 26Q1 / 26Q2 | H18: 2816.101 | I18: 3059.529 | J18: 3563.973 | K18: 4099.589 | L18: 3802.818 | M18: =IF(OR(N(H18)=0,L18=""),"",L18/H18-1) -> 0.35038409 | N18: 1645.004 | O18: 1991.371 | P18: 2556.764 | Q18: 2281.946 | R18: =IF(OR(N(L18)=0,Q18=""),"",Q18/L18) -> 0.60006711 | S18: 2425.804 | T18: =IF(OR(N(L18)=0,S18=""),"",S18/L18) -> 0.63789642 | U18: 1600.453 | V18: =IF(OR(N(L18)=0,U18=""),"",U18/L18) -> 0.42085974 | W18: 11907.851 | X18: 6327.961 | Y18: =IF(OR(N(W18)=0,X18=""),"",X18/W18) -> 0.53141083 | Z18: =IF(AA18="A","四季持續盈利",IF(AA18="B","最新季為正/波動",IF(AA18="C","虧損收窄",IF(AA18="D","虧損擴大或轉虧","數據不足")))) -> 四季持續盈利 | AA18: =IF(COUNT(N18:Q18)<4,"—",IF(MIN(N18:Q18)>0,"A",IF(Q18>0,"B",IF(Q18>N18,"C","D")))) -> A | AB18: 2026-06-30
A19: 18 | B19: AEP | C19: 受監管電力公用 | D19: American Electric Power Company, Inc. | E19: Utilities - Regulated Electric | F19: USD | G19: 25Q2 / 25Q3 / 25Q4 / 26Q1 / 26Q2 | H19: 5087 | I19: 6010.4 | J19: 5315.3 | K19: 6020 | L19: 5445 | M19: =IF(OR(N(H19)=0,L19=""),"",L19/H19-1) -> 0.070375467 | N19: 1521.4 | O19: 1180.3 | P19: 1391 | Q19: 1247 | R19: =IF(OR(N(L19)=0,Q19=""),"",Q19/L19) -> 0.22901745 | S19: 3398 | T19: =IF(OR(N(L19)=0,S19=""),"",S19/L19) -> 0.62405877 | U19: 713 | V19: =IF(OR(N(L19)=0,U19=""),"",U19/L19) -> 0.13094582 | W19: 21876 | X19: 5385 | Y19: =IF(OR(N(W19)=0,X19=""),"",X19/W19) -> 0.24616018 | Z19: =IF(AA19="A","四季持續盈利",IF(AA19="B","最新季為正/波動",IF(AA19="C","虧損收窄",IF(AA19="D","虧損擴大或轉虧","數據不足")))) -> 四季持續盈利 | AA19: =IF(COUNT(N19:Q19)<4,"—",IF(MIN(N19:Q19)>0,"A",IF(Q19>0,"B",IF(Q19>N19,"C","D")))) -> A | AB19: 2026-06-30
A20: 19 | B20: AFL | C20: 壽險與年金 | D20: Aflac Incorporated | E20: Insurance - Life | F20: USD | G20: 25Q2 / 25Q3 / 25Q4 / 26Q1 / 26Q2 | H20: 4218 | I20: 4793 | J20: 4891 | K20: 4408 | L20: 4194 | M20: =IF(OR(N(H20)=0,L20=""),"",L20/H20-1) -> -0.0056899004 | N20: 2051 | O20: 1633 | P20: 1285 | Q20: 1059 | R20: =IF(OR(N(L20)=0,Q20=""),"",Q20/L20) -> 0.25250358 | T20: =IF(OR(N(L20)=0,S20=""),"",S20/L20) | U20: 825 | V20: =IF(OR(N(L20)=0,U20=""),"",U20/L20) -> 0.19670959 | W20: 17355 | X20: 4753 | Y20: =IF(OR(N(W20)=0,X20=""),"",X20/W20) -> 0.2738692 | Z20: =IF(AA20="A","四季持續盈利",IF(AA20="B","最新季為正/波動",IF(AA20="C","虧損收窄",IF(AA20="D","虧損擴大或轉虧","數據不足")))) -> 四季持續盈利 | AA20: =IF(COUNT(N20:Q20)<4,"—",IF(MIN(N20:Q20)>0,"A",IF(Q20>0,"B",IF(Q20>N20,"C","D")))) -> A | AB20: 2026-06-30
A21: 20 | B21: AFRM | C21: 消費金融與BNPL | D21: Affirm Holdings, Inc. | E21: Credit Services | F21: USD | G21: 25Q2 / 25Q3 / 25Q4 / 26Q1 / 26Q2 | H21: 876.417 | I21: 933.337 | J21: 1123.02 | K21: 1038.765 | L21: 1165.961 | M21: =IF(OR(N(H21)=0,L21=""),"",L21/H21-1) -> 0.33037241 | N21: 173.688 | O21: 229.344 | P21: 202.19 | Q21: 265.772 | R21: =IF(OR(N(L21)=0,Q21=""),"",Q21/L21) -> 0.22794244 | S21: 804.504 | T21: =IF(OR(N(L21)=0,S21=""),"",S21/L21) -> 0.6899922 | U21: 1616.613 | V21: =IF(OR(N(L21)=0,U21=""),"",U21/L21) -> 1.3865069 | W21: 4261.083 | X21: 870.994 | Y21: =IF(OR(N(W21)=0,X21=""),"",X21/W21) -> 0.20440672 | Z21: =IF(AA21="A","四季持續盈利",IF(AA21="B","最新季為正/波動",IF(AA21="C","虧損收窄",IF(AA21="D","虧損擴大或轉虧","數據不足")))) -> 四季持續盈利 | AA21: =IF(COUNT(N21:Q21)<4,"—",IF(MIN(N21:Q21)>0,"A",IF(Q21>0,"B",IF(Q21>N21,"C","D")))) -> A | AB21: 2026-06-30
A22: 21 | B22: AG | C22: 白銀礦 | D22: First Majestic Silver Corp. | E22: Silver | F22: USD | G22: 25Q2 / 25Q3 / 25Q4 / 26Q1 / 26Q2 | H22: 264.726 | I22: 286.723 | J22: 467.716 | K22: 480.938 | L22: 414.239 | M22: =IF(OR(N(H22)=0,L22=""),"",L22/H22-1) -> 0.56478397 | N22: 76.871 | O22: 210.26 | P22: 235.978 | Q22: 198.576 | R22: =IF(OR(N(L22)=0,Q22=""),"",Q22/L22) -> 0.47937543 | S22: 223.616 | T22: =IF(OR(N(L22)=0,S22=""),"",S22/L22) -> 0.53982363 | U22: 125.893 | V22: =IF(OR(N(L22)=0,U22=""),"",U22/L22) -> 0.30391392 | W22: 1265.157 | X22: 349.931 | Y22: =IF(OR(N(W22)=0,X22=""),"",X22/W22) -> 0.27659097 | Z22: =IF(AA22="A","四季持續盈利",IF(AA22="B","最新季為正/波動",IF(AA22="C","虧損收窄",IF(AA22="D","虧損擴大或轉虧","數據不足")))) -> 四季持續盈利 | AA22: =IF(COUNT(N22:Q22)<4,"—",IF(MIN(N22:Q22)>0,"A",IF(Q22>0,"B",IF(Q22>N22,"C","D")))) -> A | AB22: 2026-06-30
A23: 22 | B23: AI | C23: — | D23: C3.ai, Inc. | E23: G3 AI | F23: USD | G23: 25Q3 / 25Q4 / 26Q1 / 26Q2 / 26Q3 | H23: 70.261 | I23: 75.147 | J23: 53.26 | K23: 51.6 | M23: =IF(OR(N(H23)=0,L23=""),"",L23/H23-1) | N23: -112.113 | O23: -140.408 | P23: -110.33 | R23: =IF(OR(N(L23)=0,Q23=""),"",Q23/L23) | T23: =IF(OR(N(L23)=0,S23=""),"",S23/L23) | V23: =IF(OR(N(L23)=0,U23=""),"",U23/L23) | W23: 250.268 | X23: -487.67 | Y23: =IF(OR(N(W23)=0,X23=""),"",X23/W23) -> -1.9485911 | Z23: =IF(AA23="A","四季持續盈利",IF(AA23="B","最新季為正/波動",IF(AA23="C","虧損收窄",IF(AA23="D","虧損擴大或轉虧","數據不足")))) -> 數據不足 | AA23: =IF(COUNT(N23:Q23)<4,"—",IF(MIN(N23:Q23)>0,"A",IF(Q23>0,"B",IF(Q23>N23,"C","D")))) -> — | AB23: 2026-07-31
A24: 23 | B24: AIG | C24: 產險與再保 | D24: American International Group, Inc. | E24: Insurance - Diversified | F24: USD | G24: 25Q2 / 25Q3 / 25Q4 / 26Q1 / 26Q2 | H24: 7041 | I24: 6402 | J24: 6557 | K24: 6616 | L24: 7086 | M24: =IF(OR(N(H24)=0,L24=""),"",L24/H24-1) -> 0.0063911376 | N24: 813 | O24: 766 | P24: 1087 | Q24: 1364 | R24: =IF(OR(N(L24)=0,Q24=""),"",Q24/L24) -> 0.19249224 | T24: =IF(OR(N(L24)=0,S24=""),"",S24/L24) | U24: 948 | V24: =IF(OR(N(L24)=0,U24=""),"",U24/L24) -> 0.13378493 | W24: 26774 | X24: 4275 | Y24: =IF(OR(N(W24)=0,X24=""),"",X24/W24) -> 0.15966983 | Z24: =IF(AA24="A","四季持續盈利",IF(AA24="B","最新季為正/波動",IF(AA24="C","虧損收窄",IF(AA24="D","虧損擴大或轉虧","數據不足")))) -> 四季持續盈利 | AA24: =IF(COUNT(N24:Q24)<4,"—",IF(MIN(N24:Q24)>0,"A",IF(Q24>0,"B",IF(Q24>N24,"C","D")))) -> A | AB24: 2026-06-30
A25: 24 | B25: AJG | C25: 保險經紀 | D25: Arthur J. Gallagher & Co. | E25: Insurance Brokers | F25: USD | G25: 25Q2 / 25Q3 / 25Q4 / 26Q1 / 26Q2 | H25: 3222 | I25: 3365.6 | J25: 3628.2 | K25: 4758 | L25: 4003 | M25: =IF(OR(N(H25)=0,L25=""),"",L25/H25-1) -> 0.24239603 | N25: 536.6 | O25: 348.1 | P25: 1218 | Q25: 588 | R25: =IF(OR(N(L25)=0,Q25=""),"",Q25/L25) -> 0.14688983 | S25: 1625 | T25: =IF(OR(N(L25)=0,S25=""),"",S25/L25) -> 0.40594554 | U25: 324 | V25: =IF(OR(N(L25)=0,U25=""),"",U25/L25) -> 0.080939296 | W25: 13942 | X25: 2556 | Y25: =IF(OR(N(W25)=0,X25=""),"",X25/W25) -> 0.18333094 | Z25: =IF(AA25="A","四季持續盈利",IF(AA25="B","最新季為正/波動",IF(AA25="C","虧損收窄",IF(AA25="D","虧損擴大或轉虧","數據不足")))) -> 四季持續盈利 | AA25: =IF(COUNT(N25:Q25)<4,"—",IF(MIN(N25:Q25)>0,"A",IF(Q25>0,"B",IF(Q25>N25,"C","D")))) -> A | AB25: 2026-06-30
A26: 25 | B26: ALAB | C26: — | D26: Astera Labs, Inc. | E26: D3 高速互連 | F26: USD | G26: 25Q2 / 25Q3 / 25Q4 / 26Q1 / 26Q2 | H26: 191.925 | I26: 230.575 | J26: 270.583 | K26: 308.361 | L26: 392.4 | M26: =IF(OR(N(H26)=0,L26=""),"",L26/H26-1) -> 1.0445487 | N26: 55.406 | O26: 66.958 | P26: 61.833 | Q26: 89.248 | R26: =IF(OR(N(L26)=0,Q26=""),"",Q26/L26) -> 0.22744139 | S26: 287.567 | T26: =IF(OR(N(L26)=0,S26=""),"",S26/L26) -> 0.73284149 | U26: 153.088 | V26: =IF(OR(N(L26)=0,U26=""),"",U26/L26) -> 0.39013252 | W26: 852.525 | X26: 173.423 | Y26: =IF(OR(N(W26)=0,X26=""),"",X26/W26) -> 0.20342277 | Z26: =IF(AA26="A","四季持續盈利",IF(AA26="B","最新季為正/波動",IF(AA26="C","虧損收窄",IF(AA26="D","虧損擴大或轉虧","數據不足")))) -> 四季持續盈利 | AA26: =IF(COUNT(N26:Q26)<4,"—",IF(MIN(N26:Q26)>0,"A",IF(Q26>0,"B",IF(Q26>N26,"C","D")))) -> A | AB26: 2026-06-30
A27: 26 | B27: ALB | C27: 特種化工 | D27: Albemarle Corporation | E27: Specialty Chemicals | F27: USD | G27: 25Q2 / 25Q3 / 25Q4 / 26Q1 / 26Q2 | H27: 1329.992 | I27: 1307.829 | J27: 1428.031 | K27: 1428.731 | L27: 1743.313 | M27: =IF(OR(N(H27)=0,L27=""),"",L27/H27-1) -> 0.31076954 | N27: -33.641 | O27: 30.253 | P27: 354.39 | Q27: 460.281 | R27: =IF(OR(N(L27)=0,Q27=""),"",Q27/L27) -> 0.2640266 | S27: 590.301 | T27: =IF(OR(N(L27)=0,S27=""),"",S27/L27) -> 0.33860873 | U27: 479.959 | V27: =IF(OR(N(L27)=0,U27=""),"",U27/L27) -> 0.2753143 | W27: 5142.733 | X27: 67.285 | Y27: =IF(OR(N(W27)=0,X27=""),"",X27/W27) -> 0.01308351 | Z27: =IF(AA27="A","四季持續盈利",IF(AA27="B","最新季為正/波動",IF(AA27="C","虧損收窄",IF(AA27="D","虧損擴大或轉虧","數據不足")))) -> 最新季為正/波動 | AA27: =IF(COUNT(N27:Q27)<4,"—",IF(MIN(N27:Q27)>0,"A",IF(Q27>0,"B",IF(Q27>N27,"C","D")))) -> B | AB27: 2026-06-30
A28: 27 | B28: ALEC | C28: 臨床期中小型生技 | D28: Alector, Inc. | E28: Biotechnology | F28: USD | G28: 25Q2 / 25Q3 / 25Q4 / 26Q1 / 26Q2 | H28: 7.874 | I28: 3.26 | J28: 6.237 | K28: 1.046 | L28: 3.32 | M28: =IF(OR(N(H28)=0,L28=""),"",L28/H28-1) -> -0.57835916 | N28: -37.608 | O28: -39.566 | P28: -24.919 | Q28: -24.393 | R28: =IF(OR(N(L28)=0,Q28=""),"",Q28/L28) -> -7.3472892 | T28: =IF(OR(N(L28)=0,S28=""),"",S28/L28) | U28: -22.99 | V28: =IF(OR(N(L28)=0,U28=""),"",U28/L28) -> -6.9246988 | W28: 21.045 | X28: -156.007 | Y28: =IF(OR(N(W28)=0,X28=""),"",X28/W28) -> -7.4130197 | Z28: =IF(AA28="A","四季持續盈利",IF(AA28="B","最新季為正/波動",IF(AA28="C","虧損收窄",IF(AA28="D","虧損擴大或轉虧","數據不足")))) -> 虧損收窄 | AA28: =IF(COUNT(N28:Q28)<4,"—",IF(MIN(N28:Q28)>0,"A",IF(Q28>0,"B",IF(Q28>N28,"C","D")))) -> C | AB28: 2026-06-30
A29: 28 | B29: ALLO | C29: 腫瘤與細胞治療 | D29: Allogene Therapeutics, Inc. | E29: Biotechnology | F29: USD | G29: 25Q2 / 25Q3 / 25Q4 / 26Q1 / 26Q2 | H29: 0 | I29: 0 | J29: 0 | K29: 0 | L29: 4.64 | M29: =IF(OR(N(H29)=0,L29=""),"",L29/H29-1) | N29: -44.901 | O29: -42.404 | P29: -46.092 | Q29: -46.92 | R29: =IF(OR(N(L29)=0,Q29=""),"",Q29/L29) -> -10.112069 | T29: =IF(OR(N(L29)=0,S29=""),"",S29/L29) | U29: -42.677 | V29: =IF(OR(N(L29)=0,U29=""),"",U29/L29) -> -9.1976293 | W29: 0 | X29: -206.933 | Y29: =IF(OR(N(W29)=0,X29=""),"",X29/W29) | Z29: =IF(AA29="A","四季持續盈利",IF(AA29="B","最新季為正/波動",IF(AA29="C","虧損收窄",IF(AA29="D","虧損擴大或轉虧","數據不足")))) -> 虧損擴大或轉虧 | AA29: =IF(COUNT(N29:Q29)<4,"—",IF(MIN(N29:Q29)>0,"A",IF(Q29>0,"B",IF(Q29>N29,"C","D")))) -> D | AB29: 2026-06-30
A30: 29 | B30: ALOY | C30: 稀土與關鍵礦產 | D30: REalloys Inc. | E30: Other Industrial Metals & Mining | F30: USD | G30: 25Q1 / 25Q2 / 26Q1 / 26Q2 | H30: 0 | I30: 0.44 | J30: 0.706 | K30: 0.804 | M30: =IF(OR(N(H30)=0,L30=""),"",L30/H30-1) | N30: -0.867 | O30: -0.902 | P30: -87.657 | Q30: -36.804 | R30: =IF(OR(N(L30)=0,Q30=""),"",Q30/L30) -> -45.776119 | S30: 0.475 | T30: =IF(OR(N(L30)=0,S30=""),"",S30/L30) -> 0.59079602 | U30: -36.818 | V30: =IF(OR(N(L30)=0,U30=""),"",U30/L30) -> -45.793532 | Y30: =IF(OR(N(W30)=0,X30=""),"",X30/W30) | Z30: =IF(AA30="A","四季持續盈利",IF(AA30="B","最新季為正/波動",IF(AA30="C","虧損收窄",IF(AA30="D","虧損擴大或轉虧","數據不足")))) -> 虧損擴大或轉虧 | AA30: =IF(COUNT(N30:Q30)<4,"—",IF(MIN(N30:Q30)>0,"A",IF(Q30>0,"B",IF(Q30>N30,"C","D")))) -> D | AB30: 2026-06-30
A31: 30 | B31: ALT | C31: GLP-1減重與代謝 | D31: Altimmune, Inc. | E31: Biotechnology | F31: USD | G31: 25Q2 / 25Q3 / 25Q4 / 26Q1 / 26Q2 | H31: 0.005 | I31: 0.005 | J31: 0.026 | K31: 0 | L31: 0 | M31: =IF(OR(N(H31)=0,L31=""),"",L31/H31-1) -> -1 | N31: -20.859 | O31: -28.893 | P31: -24.244 | Q31: -26.229 | R31: =IF(OR(N(L31)=0,Q31=""),"",Q31/L31) | T31: =IF(OR(N(L31)=0,S31=""),"",S31/L31) | U31: -22.825 | V31: =IF(OR(N(L31)=0,U31=""),"",U31/L31) | W31: 0.041 | X31: -94.489 | Y31: =IF(OR(N(W31)=0,X31=""),"",X31/W31) -> -2304.6098 | Z31: =IF(AA31="A","四季持續盈利",IF(AA31="B","最新季為正/波動",IF(AA31="C","虧損收窄",IF(AA31="D","虧損擴大或轉虧","數據不足")))) -> 虧損擴大或轉虧 | AA31: =IF(COUNT(N31:Q31)<4,"—",IF(MIN(N31:Q31)>0,"A",IF(Q31>0,"B",IF(Q31>N31,"C","D")))) -> D | AB31: 2026-06-30
A32: 31 | B32: AMAT | C32: 半導體設備 | D32: Applied Materials, Inc. | E32: B2 半導體前段設備 | F32: USD | G32: 25Q3 / 25Q4 / 26Q1 / 26Q2 / 26Q3 | H32: 7302 | I32: 6800 | J32: 7012 | K32: 7910 | L32: 9115 | M32: =IF(OR(N(H32)=0,L32=""),"",L32/H32-1) -> 0.24828814 | N32: 1893 | O32: 2096 | P32: 2523 | Q32: 3075 | R32: =IF(OR(N(L32)=0,Q32=""),"",Q32/L32) -> 0.33735601 | S32: 4586 | T32: =IF(OR(N(L32)=0,S32=""),"",S32/L32) -> 0.50312671 | U32: 2538 | V32: =IF(OR(N(L32)=0,U32=""),"",U32/L32) -> 0.27844213 | W32: 28368 | X32: 8470 | Y32: =IF(OR(N(W32)=0,X32=""),"",X32/W32) -> 0.29857586 | Z32: =IF(AA32="A","四季持續盈利",IF(AA32="B","最新季為正/波動",IF(AA32="C","虧損收窄",IF(AA32="D","虧損擴大或轉虧","數據不足")))) -> 四季持續盈利 | AA32: =IF(COUNT(N32:Q32)<4,"—",IF(MIN(N32:Q32)>0,"A",IF(Q32>0,"B",IF(Q32>N32,"C","D")))) -> A | AB32: 2026-07-31
A33: 32 | B33: AMD | C33: AI加速晶片/GPU | D33: Advanced Micro Devices, Inc. | E33: A1 GPU | F33: USD | G33: 25Q2 / 25Q3 / 25Q4 / 26Q1 / 26Q2 | H33: 7685 | I33: 9246 | J33: 10270 | K33: 10253 | L33: 11536 | M33: =IF(OR(N(H33)=0,L33=""),"",L33/H33-1) -> 0.50110605 | N33: 1270 | O33: 1752 | P33: 1476 | Q33: 1990 | R33: =IF(OR(N(L33)=0,Q33=""),"",Q33/L33) -> 0.17250347 | S33: 6203 | T33: =IF(OR(N(L33)=0,S33=""),"",S33/L33) -> 0.53770804 | U33: 2297 | V33: =IF(OR(N(L33)=0,U33=""),"",U33/L33) -> 0.19911581 | W33: 34639 | X33: 3694 | Y33: =IF(OR(N(W33)=0,X33=""),"",X33/W33) -> 0.1066428 | Z33: =IF(AA33="A","四季持續盈利",IF(AA33="B","最新季為正/波動",IF(AA33="C","虧損收窄",IF(AA33="D","虧損擴大或轉虧","數據不足")))) -> 四季持續盈利 | AA33: =IF(COUNT(N33:Q33)<4,"—",IF(MIN(N33:Q33)>0,"A",IF(Q33>0,"B",IF(Q33>N33,"C","D")))) -> A | AB33: 2026-06-30
A34: 33 | B34: AMG | C34: 資產管理 | D34: Affiliated Managers Group, Inc. | E34: Asset Management | F34: USD | G34: 25Q2 / 25Q3 / 25Q4 / 26Q1 / 26Q2 | H34: 493.2 | I34: 528 | J34: 556.6 | K34: 544.9 | L34: 640.7 | M34: =IF(OR(N(H34)=0,L34=""),"",L34/H34-1) -> 0.29906732 | N34: 165.1 | O34: 99.8 | P34: 98.7 | Q34: 207.8 | R34: =IF(OR(N(L34)=0,Q34=""),"",Q34/L34) -> 0.32433276 | S34: 324.6 | T34: =IF(OR(N(L34)=0,S34=""),"",S34/L34) -> 0.50663337 | U34: 185.9 | V34: =IF(OR(N(L34)=0,U34=""),"",U34/L34) -> 0.2901514 | W34: 2074.4 | X34: 475.3 | Y34: =IF(OR(N(W34)=0,X34=""),"",X34/W34) -> 0.22912649 | Z34: =IF(AA34="A","四季持續盈利",IF(AA34="B","最新季為正/波動",IF(AA34="C","虧損收窄",IF(AA34="D","虧損擴大或轉虧","數據不足")))) -> 四季持續盈利 | AA34: =IF(COUNT(N34:Q34)<4,"—",IF(MIN(N34:Q34)>0,"A",IF(Q34>0,"B",IF(Q34>N34,"C","D")))) -> A | AB34: 2026-06-30
A35: 34 | B35: AMGN | C35: 大型生物科技 | D35: Amgen Inc. | E35: Drug Manufacturers - General | F35: USD | G35: 25Q2 / 25Q3 / 25Q4 / 26Q1 / 26Q2 | H35: 9179 | I35: 9557 | J35: 9866 | K35: 8618 | L35: 10054 | M35: =IF(OR(N(H35)=0,L35=""),"",L35/H35-1) -> 0.095326288 | N35: 2526 | O35: 2720 | P35: 2666 | Q35: 3514 | R35: =IF(OR(N(L35)=0,Q35=""),"",Q35/L35) -> 0.34951263 | S35: 7243 | T35: =IF(OR(N(L35)=0,S35=""),"",S35/L35) -> 0.72040979 | U35: 2375 | V35: =IF(OR(N(L35)=0,U35=""),"",U35/L35) -> 0.23622439 | W35: 36751 | X35: 9080 | Y35: =IF(OR(N(W35)=0,X35=""),"",X35/W35) -> 0.24706811 | Z35: =IF(AA35="A","四季持續盈利",IF(AA35="B","最新季為正/波動",IF(AA35="C","虧損收窄",IF(AA35="D","虧損擴大或轉虧","數據不足")))) -> 四季持續盈利 | AA35: =IF(COUNT(N35:Q35)<4,"—",IF(MIN(N35:Q35)>0,"A",IF(Q35>0,"B",IF(Q35>N35,"C","D")))) -> A | AB35: 2026-06-30
A36: 35 | B36: AMH | C36: 住宅公寓REIT | D36: American Homes 4 Rent | E36: REIT - Residential | F36: USD | G36: 25Q2 / 25Q3 / 25Q4 / 26Q1 / 26Q2 | H36: 457.503 | I36: 478.464 | J36: 454.991 | K36: 472.024 | L36: 470.104 | M36: =IF(OR(N(H36)=0,L36=""),"",L36/H36-1) -> 0.027542989 | N36: 116.317 | O36: 118.787 | P36: 121.355 | Q36: 125.052 | R36: =IF(OR(N(L36)=0,Q36=""),"",Q36/L36) -> 0.26600922 | S36: 274.317 | T36: =IF(OR(N(L36)=0,S36=""),"",S36/L36) -> 0.58352407 | U36: 117.112 | V36: =IF(OR(N(L36)=0,U36=""),"",U36/L36) -> 0.24911934 | W36: 1850.234 | X36: 464.125 | Y36: =IF(OR(N(W36)=0,X36=""),"",X36/W36) -> 0.25084665 | Z36: =IF(AA36="A","四季持續盈利",IF(AA36="B","最新季為正/波動",IF(AA36="C","虧損收窄",IF(AA36="D","虧損擴大或轉虧","數據不足")))) -> 四季持續盈利 | AA36: =IF(COUNT(N36:Q36)<4,"—",IF(MIN(N36:Q36)>0,"A",IF(Q36>0,"B",IF(Q36>N36,"C","D")))) -> A | AB36: 2026-06-30
A37: 36 | B37: AMKR | C37: — | D37: Amkor Technology, Inc. | E37: B3 先進封裝 | F37: USD | G37: 25Q2 / 25Q3 / 25Q4 / 26Q1 / 26Q2 | H37: 1511.392 | I37: 1986.968 | J37: 1888.046 | K37: 1684.701 | L37: 1897.965 | M37: =IF(OR(N(H37)=0,L37=""),"",L37/H37-1) -> 0.25577282 | N37: 158.927 | O37: 184.968 | P37: 100.287 | Q37: 199.854 | R37: =IF(OR(N(L37)=0,Q37=""),"",Q37/L37) -> 0.1052991 | S37: 318.59 | T37: =IF(OR(N(L37)=0,S37=""),"",S37/L37) -> 0.16785873 | U37: 173.753 | V37: =IF(OR(N(L37)=0,U37=""),"",U37/L37) -> 0.091546999 | W37: 6707.981 | X37: 467.385 | Y37: =IF(OR(N(W37)=0,X37=""),"",X37/W37) -> 0.069675958 | Z37: =IF(AA37="A","四季持續盈利",IF(AA37="B","最新季為正/波動",IF(AA37="C","虧損收窄",IF(AA37="D","虧損擴大或轉虧","數據不足")))) -> 四季持續盈利 | AA37: =IF(COUNT(N37:Q37)<4,"—",IF(MIN(N37:Q37)>0,"A",IF(Q37>0,"B",IF(Q37>N37,"C","D")))) -> A | AB37: 2026-06-30
A38: 37 | B38: AMR | C38: 煤炭 | D38: Alpha Metallurgical Resources, Inc. | E38: Coking Coal | F38: USD | G38: 25Q2 / 25Q3 / 25Q4 / 26Q1 / 26Q2 | H38: 550.274 | I38: 526.778 | J38: 520.472 | K38: 524.987 | L38: 492.856 | M38: =IF(OR(N(H38)=0,L38=""),"",L38/H38-1) -> -0.10434438 | N38: -2.522 | O38: -21.324 | P38: -10.432 | Q38: -10.5 | R38: =IF(OR(N(L38)=0,Q38=""),"",Q38/L38) -> -0.021304397 | S38: 12.273 | T38: =IF(OR(N(L38)=0,S38=""),"",S38/L38) -> 0.024901797 | U38: -12.252 | V38: =IF(OR(N(L38)=0,U38=""),"",U38/L38) -> -0.024859188 | W38: 2129.481 | X38: -61.366 | Y38: =IF(OR(N(W38)=0,X38=""),"",X38/W38) -> -0.02881735 | Z38: =IF(AA38="A","四季持續盈利",IF(AA38="B","最新季為正/波動",IF(AA38="C","虧損收窄",IF(AA38="D","虧損擴大或轉虧","數據不足")))) -> 虧損擴大或轉虧 | AA38: =IF(COUNT(N38:Q38)<4,"—",IF(MIN(N38:Q38)>0,"A",IF(Q38>0,"B",IF(Q38>N38,"C","D")))) -> D | AB38: 2026-06-30
A39: 38 | B39: AMS | C39: — | D39: American Shared Hospital Services | E39: D9 光模塊上游 | F39: USD | G39: 25Q2 / 25Q3 / 25Q4 / 26Q1 / 26Q2 | H39: 7.071 | I39: 7.171 | J39: 7.728 | K39: 7.084 | L39: 8.43 | M39: =IF(OR(N(H39)=0,L39=""),"",L39/H39-1) -> 0.19219347 | N39: 0.048 | O39: -1.08 | P39: -0.622 | Q39: -0.609 | R39: =IF(OR(N(L39)=0,Q39=""),"",Q39/L39) -> -0.072241993 | S39: 1.433 | T39: =IF(OR(N(L39)=0,S39=""),"",S39/L39) -> 0.16998814 | U39: -0.514 | V39: =IF(OR(N(L39)=0,U39=""),"",U39/L39) -> -0.060972716 | W39: 28.082 | X39: -2.014 | Y39: =IF(OR(N(W39)=0,X39=""),"",X39/W39) -> -0.071718539 | Z39: =IF(AA39="A","四季持續盈利",IF(AA39="B","最新季為正/波動",IF(AA39="C","虧損收窄",IF(AA39="D","虧損擴大或轉虧","數據不足")))) -> 虧損擴大或轉虧 | AA39: =IF(COUNT(N39:Q39)<4,"—",IF(MIN(N39:Q39)>0,"A",IF(Q39>0,"B",IF(Q39>N39,"C","D")))) -> D | AB39: 2026-06-30
A40: 39 | B40: AMT | C40: 通訊塔REIT | D40: American Tower Corporation | E40: REIT - Specialty | F40: USD | G40: 25Q2 / 25Q3 / 25Q4 / 26Q1 / 26Q2 | H40: 2626.9 | I40: 2717.4 | J40: 2737.5 | K40: 2737.5 | L40: 2749.1 | M40: =IF(OR(N(H40)=0,L40=""),"",L40/H40-1) -> 0.04651871 | N40: 1233.3 | O40: 1244.1 | P40: 1239.2 | Q40: 1268.8 | R40: =IF(OR(N(L40)=0,Q40=""),"",Q40/L40) -> 0.46153287 | S40: 2007.8 | T40: =IF(OR(N(L40)=0,S40=""),"",S40/L40) -> 0.73034811 | U40: 867.5 | V40: =IF(OR(N(L40)=0,U40=""),"",U40/L40) -> 0.31555782 | W40: 10644.6 | X40: 4929.2 | Y40: =IF(OR(N(W40)=0,X40=""),"",X40/W40) -> 0.46307048 | Z40: =IF(AA40="A","四季持續盈利",IF(AA40="B","最新季為正/波動",IF(AA40="C","虧損收窄",IF(AA40="D","虧損擴大或轉虧","數據不足")))) -> 四季持續盈利 | AA40: =IF(COUNT(N40:Q40)<4,"—",IF(MIN(N40:Q40)>0,"A",IF(Q40>0,"B",IF(Q40>N40,"C","D")))) -> A | AB40: 2026-06-30
A41: 40 | B41: AMZN | C41: 雲端基建/IaaS/Neocloud、電商平台 | D41: Amazon.com, Inc. | E41: AA2 Hyperscaler | F41: USD | G41: 25Q2 / 25Q3 / 25Q4 / 26Q1 / 26Q2 | H41: 167702 | I41: 180169 | J41: 213386 | K41: 181519 | M41: =IF(OR(N(H41)=0,L41=""),"",L41/H41-1) | N41: 17422 | O41: 24977 | P41: 23852 | R41: =IF(OR(N(L41)=0,Q41=""),"",Q41/L41) | T41: =IF(OR(N(L41)=0,S41=""),"",S41/L41) | V41: =IF(OR(N(L41)=0,U41=""),"",U41/L41) | W41: 716924 | X41: 79975 | Y41: =IF(OR(N(W41)=0,X41=""),"",X41/W41) -> 0.11155297 | Z41: =IF(AA41="A","四季持續盈利",IF(AA41="B","最新季為正/波動",IF(AA41="C","虧損收窄",IF(AA41="D","虧損擴大或轉虧","數據不足")))) -> 數據不足 | AA41: =IF(COUNT(N41:Q41)<4,"—",IF(MIN(N41:Q41)>0,"A",IF(Q41>0,"B",IF(Q41>N41,"C","D")))) -> — | AB41: 2026-06-30
A42: 41 | B42: ANET | C42: AI資料中心建設 | D42: Arista Networks, Inc. | E42: D4 網絡交換 | F42: USD | G42: 25Q2 / 25Q3 / 25Q4 / 26Q1 / 26Q2 | H42: 2204.8 | I42: 2308.3 | J42: 2487.8 | K42: 2709 | L42: 3035.7 | M42: =IF(OR(N(H42)=0,L42=""),"",L42/H42-1) -> 0.37685958 | N42: 978.2 | O42: 1032.9 | P42: 1157.8 | Q42: 1378 | R42: =IF(OR(N(L42)=0,Q42=""),"",Q42/L42) -> 0.45393155 | S42: 1910.3 | T42: =IF(OR(N(L42)=0,S42=""),"",S42/L42) -> 0.62927826 | U42: 1212.9 | V42: =IF(OR(N(L42)=0,U42=""),"",U42/L42) -> 0.39954541 | W42: 9005.7 | X42: 3856.1 | Y42: =IF(OR(N(W42)=0,X42=""),"",X42/W42) -> 0.42818437 | Z42: =IF(AA42="A","四季持續盈利",IF(AA42="B","最新季為正/波動",IF(AA42="C","虧損收窄",IF(AA42="D","虧損擴大或轉虧","數據不足")))) -> 四季持續盈利 | AA42: =IF(COUNT(N42:Q42)<4,"—",IF(MIN(N42:Q42)>0,"A",IF(Q42>0,"B",IF(Q42>N42,"C","D")))) -> A | AB42: 2026-06-30
A43: 42 | B43: AON | C43: 保險經紀 | D43: Aon plc | E43: Insurance Brokers | F43: USD | G43: 25Q2 / 25Q3 / 25Q4 / 26Q1 / 26Q2 | H43: 4155 | I43: 3997 | J43: 4300 | K43: 5034 | L43: 4246 | M43: =IF(OR(N(H43)=0,L43=""),"",L43/H43-1) -> 0.021901324 | N43: 848 | O43: 1337 | P43: 1807 | Q43: 1011 | R43: =IF(OR(N(L43)=0,Q43=""),"",Q43/L43) -> 0.23810645 | S43: 1975 | T43: =IF(OR(N(L43)=0,S43=""),"",S43/L43) -> 0.46514366 | U43: 551 | V43: =IF(OR(N(L43)=0,U43=""),"",U43/L43) -> 0.12976919 | W43: 17181 | X43: 4709 | Y43: =IF(OR(N(W43)=0,X43=""),"",X43/W43) -> 0.27408183 | Z43: =IF(AA43="A","四季持續盈利",IF(AA43="B","最新季為正/波動",IF(AA43="C","虧損收窄",IF(AA43="D","虧損擴大或轉虧","數據不足")))) -> 四季持續盈利 | AA43: =IF(COUNT(N43:Q43)<4,"—",IF(MIN(N43:Q43)>0,"A",IF(Q43>0,"B",IF(Q43>N43,"C","D")))) -> A | AB43: 2026-06-30
A44: 43 | B44: APD | C44: 特種化工 | D44: Air Products and Chemicals, Inc. | E44: B10 半導體材料②光刻膠/特氣 | F44: USD | G44: 25Q2 / 25Q3 / 25Q4 / 26Q1 / 26Q2 | H44: 3022.7 | I44: 3166.9 | J44: 3102.5 | K44: 3171.8 | L44: 3161 | M44: =IF(OR(N(H44)=0,L44=""),"",L44/H44-1) -> 0.045753796 | N44: 811.8 | O44: 756.5 | P44: 752.7 | Q44: 810.3 | R44: =IF(OR(N(L44)=0,Q44=""),"",Q44/L44) -> 0.25634293 | S44: 1036 | T44: =IF(OR(N(L44)=0,S44=""),"",S44/L44) -> 0.32774438 | U44: -1440.8 | V44: =IF(OR(N(L44)=0,U44=""),"",U44/L44) -> -0.45580512 | W44: 12037.3 | X44: 2889 | Y44: =IF(OR(N(W44)=0,X44=""),"",X44/W44) -> 0.24000399 | Z44: =IF(AA44="A","四季持續盈利",IF(AA44="B","最新季為正/波動",IF(AA44="C","虧損收窄",IF(AA44="D","虧損擴大或轉虧","數據不足")))) -> 四季持續盈利 | AA44: =IF(COUNT(N44:Q44)<4,"—",IF(MIN(N44:Q44)>0,"A",IF(Q44>0,"B",IF(Q44>N44,"C","D")))) -> A | AB44: 2026-06-30
A45: 44 | B45: APH | C45: 電子硬件與EMS/連接器 | D45: Amphenol Corporation | E45: D5 連接器 | F45: USD | G45: 25Q2 / 25Q3 / 25Q4 / 26Q1 / 26Q2 | H45: 5650.3 | I45: 6194.4 | J45: 6439 | K45: 7620.1 | M45: =IF(OR(N(H45)=0,L45=""),"",L45/H45-1) | N45: 1702.3 | O45: 1770.1 | P45: 1948.7 | R45: =IF(OR(N(L45)=0,Q45=""),"",Q45/L45) | T45: =IF(OR(N(L45)=0,S45=""),"",S45/L45) | V45: =IF(OR(N(L45)=0,U45=""),"",U45/L45) | W45: 23094.7 | X45: 5972 | Y45: =IF(OR(N(W45)=0,X45=""),"",X45/W45) -> 0.25858747 | Z45: =IF(AA45="A","四季持續盈利",IF(AA45="B","最新季為正/波動",IF(AA45="C","虧損收窄",IF(AA45="D","虧損擴大或轉虧","數據不足")))) -> 數據不足 | AA45: =IF(COUNT(N45:Q45)<4,"—",IF(MIN(N45:Q45)>0,"A",IF(Q45>0,"B",IF(Q45>N45,"C","D")))) -> — | AB45: 2026-06-30
A46: 45 | B46: APLD | C46: — | D46: Applied Digital Corporation | E46: AA1 Neo | F46: USD | G46: 25Q2 / 25Q3 / 25Q4 / 26Q1 / 26Q2 | H46: -33.3 | I46: 64.216 | J46: 126.589 | K46: 126.637 | L46: 258.749 | M46: =IF(OR(N(H46)=0,L46=""),"",L46/H46-1) -> -8.7702402 | N46: -20.542 | O46: -30.957 | P46: -25.918 | Q46: -124.764 | R46: =IF(OR(N(L46)=0,Q46=""),"",Q46/L46) -> -0.48218157 | S46: 40.518 | T46: =IF(OR(N(L46)=0,S46=""),"",S46/L46) -> 0.15659191 | U46: -110.162 | V46: =IF(OR(N(L46)=0,U46=""),"",U46/L46) -> -0.42574851 | W46: 611.311 | X46: -174.414 | Y46: =IF(OR(N(W46)=0,X46=""),"",X46/W46) -> -0.2853114 | Z46: =IF(AA46="A","四季持續盈利",IF(AA46="B","最新季為正/波動",IF(AA46="C","虧損收窄",IF(AA46="D","虧損擴大或轉虧","數據不足")))) -> 虧損擴大或轉虧 | AA46: =IF(COUNT(N46:Q46)<4,"—",IF(MIN(N46:Q46)>0,"A",IF(Q46>0,"B",IF(Q46>N46,"C","D")))) -> D | AB46: 2026-05-31
A47: 46 | B47: APO | C47: 另類資產與私募信貸 | D47: Apollo Global Management, Inc. | E47: Asset Management | F47: USD | G47: 25Q2 / 25Q3 / 25Q4 / 26Q1 / 26Q2 | H47: 6814 | I47: 9823 | J47: 9864 | K47: 5057 | L47: 11153 | M47: =IF(OR(N(H47)=0,L47=""),"",L47/H47-1) -> 0.63677722 | N47: 3172 | O47: 2105 | P47: 794 | Q47: 2850 | R47: =IF(OR(N(L47)=0,Q47=""),"",Q47/L47) -> 0.25553663 | S47: 10718 | T47: =IF(OR(N(L47)=0,S47=""),"",S47/L47) -> 0.96099704 | U47: 1361 | V47: =IF(OR(N(L47)=0,U47=""),"",U47/L47) -> 0.12202995 | W47: 32049 | X47: 8258 | Y47: =IF(OR(N(W47)=0,X47=""),"",X47/W47) -> 0.25766795 | Z47: =IF(AA47="A","四季持續盈利",IF(AA47="B","最新季為正/波動",IF(AA47="C","虧損收窄",IF(AA47="D","虧損擴大或轉虧","數據不足")))) -> 四季持續盈利 | AA47: =IF(COUNT(N47:Q47)<4,"—",IF(MIN(N47:Q47)>0,"A",IF(Q47>0,"B",IF(Q47>N47,"C","D")))) -> A | AB47: 2026-06-30
A48: 47 | B48: APTV | C48: 傳統汽車與零部件 | D48: Aptiv PLC | E48: Auto Parts | F48: USD | G48: 25Q2 / 25Q3 / 25Q4 / 26Q1 / 26Q2 | H48: 3199 | I48: 5212 | J48: 5153 | K48: 5086 | L48: 3274 | M48: =IF(OR(N(H48)=0,L48=""),"",L48/H48-1) -> 0.023444827 | N48: 533 | O48: 461 | P48: 440 | Q48: 391 | R48: =IF(OR(N(L48)=0,Q48=""),"",Q48/L48) -> 0.11942578 | S48: 775 | T48: =IF(OR(N(L48)=0,S48=""),"",S48/L48) -> 0.2367135 | U48: 248 | V48: =IF(OR(N(L48)=0,U48=""),"",U48/L48) -> 0.07574832 | W48: 20398 | X48: 2017 | Y48: =IF(OR(N(W48)=0,X48=""),"",X48/W48) -> 0.098882243 | Z48: =IF(AA48="A","四季持續盈利",IF(AA48="B","最新季為正/波動",IF(AA48="C","虧損收窄",IF(AA48="D","虧損擴大或轉虧","數據不足")))) -> 四季持續盈利 | AA48: =IF(COUNT(N48:Q48)<4,"—",IF(MIN(N48:Q48)>0,"A",IF(Q48>0,"B",IF(Q48>N48,"C","D")))) -> A | AB48: 2026-06-30
A49: 48 | B49: ARES | C49: 另類資產與私募信貸 | D49: Ares Management Corporation | E49: Asset Management | F49: USD | G49: 25Q2 / 25Q3 / 25Q4 / 26Q1 / 26Q2 | H49: 1350.128 | I49: 1657.628 | J49: 1504.921 | K49: 1396.436 | L49: 1428.61 | M49: =IF(OR(N(H49)=0,L49=""),"",L49/H49-1) -> 0.058129303 | N49: 349.412 | O49: 256.277 | P49: 227.973 | Q49: 248.633 | R49: =IF(OR(N(L49)=0,Q49=""),"",Q49/L49) -> 0.1740384 | S49: 739.95 | T49: =IF(OR(N(L49)=0,S49=""),"",S49/L49) -> 0.51795102 | U49: 150.635 | V49: =IF(OR(N(L49)=0,U49=""),"",U49/L49) -> 0.10544165 | W49: 5601.482 | X49: 892.716 | Y49: =IF(OR(N(W49)=0,X49=""),"",X49/W49) -> 0.15937139 | Z49: =IF(AA49="A","四季持續盈利",IF(AA49="B","最新季為正/波動",IF(AA49="C","虧損收窄",IF(AA49="D","虧損擴大或轉虧","數據不足")))) -> 四季持續盈利 | AA49: =IF(COUNT(N49:Q49)<4,"—",IF(MIN(N49:Q49)>0,"A",IF(Q49>0,"B",IF(Q49>N49,"C","D")))) -> A | AB49: 2026-06-30
A50: 49 | B50: ARM | C50: EDA與半導體IP | D50: Arm Holdings plc | E50: A4 運算 | F50: USD | G50: 25Q2 / 25Q3 / 25Q4 / 26Q1 / 26Q2 | H50: 1053 | I50: 1135 | J50: 1242 | K50: 1490 | L50: 1289 | M50: =IF(OR(N(H50)=0,L50=""),"",L50/H50-1) -> 0.22412156 | N50: 163 | O50: 191 | P50: 440 | Q50: 98 | R50: =IF(OR(N(L50)=0,Q50=""),"",Q50/L50) -> 0.076027929 | S50: 1253 | T50: =IF(OR(N(L50)=0,S50=""),"",S50/L50) -> 0.97207137 | U50: 270 | V50: =IF(OR(N(L50)=0,U50=""),"",U50/L50) -> 0.2094647 | W50: 4920 | X50: 908 | Y50: =IF(OR(N(W50)=0,X50=""),"",X50/W50) -> 0.18455285 | Z50: =IF(AA50="A","四季持續盈利",IF(AA50="B","最新季為正/波動",IF(AA50="C","虧損收窄",IF(AA50="D","虧損擴大或轉虧","數據不足")))) -> 四季持續盈利 | AA50: =IF(COUNT(N50:Q50)<4,"—",IF(MIN(N50:Q50)>0,"A",IF(Q50>0,"B",IF(Q50>N50,"C","D")))) -> A | AB50: 2026-06-30
A51: 50 | B51: ARVN | C51: 腫瘤與細胞治療 | D51: Arvinas, Inc. | E51: Biotechnology | F51: USD | G51: 25Q2 / 25Q3 / 25Q4 / 26Q1 / 26Q2 | H51: 22.4 | I51: 41.9 | J51: 9.5 | K51: 15.6 | L51: 249.7 | M51: =IF(OR(N(H51)=0,L51=""),"",L51/H51-1) -> 10.147321 | N51: -43.8 | O51: -74.6 | P51: -63.8 | Q51: 164.1 | R51: =IF(OR(N(L51)=0,Q51=""),"",Q51/L51) -> 0.65718863 | T51: =IF(OR(N(L51)=0,S51=""),"",S51/L51) | U51: 169.4 | V51: =IF(OR(N(L51)=0,U51=""),"",U51/L51) -> 0.6784141 | W51: 262.6 | X51: -118.5 | Y51: =IF(OR(N(W51)=0,X51=""),"",X51/W51) -> -0.45125666 | Z51: =IF(AA51="A","四季持續盈利",IF(AA51="B","最新季為正/波動",IF(AA51="C","虧損收窄",IF(AA51="D","虧損擴大或轉虧","數據不足")))) -> 最新季為正/波動 | AA51: =IF(COUNT(N51:Q51)<4,"—",IF(MIN(N51:Q51)>0,"A",IF(Q51>0,"B",IF(Q51>N51,"C","D")))) -> B | AB51: 2026-06-30
A52: 51 | B52: ASML | C52: 半導體設備 | D52: ASML Holding N.V. | E52: B2 半導體前段設備 | F52: EUR | G52: 25Q2 / 25Q3 / 25Q4 / 26Q1 / 26Q2 | H52: 7691.7 | I52: 7516 | J52: 9718.1 | K52: 8766.9 | L52: 9326.5 | M52: =IF(OR(N(H52)=0,L52=""),"",L52/H52-1) -> 0.21254079 | N52: 2468.4 | O52: 3431.1 | P52: 3157.8 | Q52: 3456.1 | R52: =IF(OR(N(L52)=0,Q52=""),"",Q52/L52) -> 0.37056774 | S52: 5035.4 | T52: =IF(OR(N(L52)=0,S52=""),"",S52/L52) -> 0.53990243 | U52: 2917.6 | V52: =IF(OR(N(L52)=0,U52=""),"",U52/L52) -> 0.31282904 | W52: 32667.3 | X52: 11301.4 | Y52: =IF(OR(N(W52)=0,X52=""),"",X52/W52) -> 0.34595452 | Z52: =IF(AA52="A","四季持續盈利",IF(AA52="B","最新季為正/波動",IF(AA52="C","虧損收窄",IF(AA52="D","虧損擴大或轉虧","數據不足")))) -> 四季持續盈利 | AA52: =IF(COUNT(N52:Q52)<4,"—",IF(MIN(N52:Q52)>0,"A",IF(Q52>0,"B",IF(Q52>N52,"C","D")))) -> A | AB52: 2026-06-30
A53: 52 | B53: ASPI | C53: 小型模組化核能SMR | D53: ASP Isotopes Inc. | E53: Specialty Chemicals | F53: USD | G53: 25Q2 / 25Q3 / 25Q4 / 26Q1 / 26Q2 | H53: 1.198 | I53: 4.889526 | J53: 16.659524 | K53: 4.18 | L53: 5.123 | M53: =IF(OR(N(H53)=0,L53=""),"",L53/H53-1) -> 3.2762938 | N53: -14.966939 | O53: -22.303139 | P53: -24.888 | Q53: -34.195 | R53: =IF(OR(N(L53)=0,Q53=""),"",Q53/L53) -> -6.6747999 | S53: 1.48 | T53: =IF(OR(N(L53)=0,S53=""),"",S53/L53) -> 0.28889323 | U53: -33.585 | V53: =IF(OR(N(L53)=0,U53=""),"",U53/L53) -> -6.5557291 | W53: 23.849 | X53: -57.191 | Y53: =IF(OR(N(W53)=0,X53=""),"",X53/W53) -> -2.398046 | Z53: =IF(AA53="A","四季持續盈利",IF(AA53="B","最新季為正/波動",IF(AA53="C","虧損收窄",IF(AA53="D","虧損擴大或轉虧","數據不足")))) -> 虧損擴大或轉虧 | AA53: =IF(COUNT(N53:Q53)<4,"—",IF(MIN(N53:Q53)>0,"A",IF(Q53>0,"B",IF(Q53>N53,"C","D")))) -> D | AB53: 2026-06-30
A54: 53 | B54: ASTS | C54: 太空與衛星、有線/寬頻/衛星 | D54: AST SpaceMobile, Inc. | E54: Communication Equipment | F54: USD | G54: 25Q2 / 25Q3 / 25Q4 / 26Q1 / 26Q2 | H54: 1.156 | I54: 14.739 | J54: 54.305 | K54: 14.735 | L54: 31.52 | M54: =IF(OR(N(H54)=0,L54=""),"",L54/H54-1) -> 26.266436 | N54: -79.676 | O54: -72.277 | P54: -149.412 | Q54: -171.666 | R54: =IF(OR(N(L54)=0,Q54=""),"",Q54/L54) -> -5.4462563 | S54: 7.953 | T54: =IF(OR(N(L54)=0,S54=""),"",S54/L54) -> 0.25231599 | U54: -230.909 | V54: =IF(OR(N(L54)=0,U54=""),"",U54/L54) -> -7.3257931 | W54: 70.918 | X54: -287.713 | Y54: =IF(OR(N(W54)=0,X54=""),"",X54/W54) -> -4.0569813 | Z54: =IF(AA54="A","四季持續盈利",IF(AA54="B","最新季為正/波動",IF(AA54="C","虧損收窄",IF(AA54="D","虧損擴大或轉虧","數據不足")))) -> 虧損擴大或轉虧 | AA54: =IF(COUNT(N54:Q54)<4,"—",IF(MIN(N54:Q54)>0,"A",IF(Q54>0,"B",IF(Q54>N54,"C","D")))) -> D | AB54: 2026-06-30
A55: 54 | B55: ASX | C55: — | D55: ASE Technology Holding Co., Ltd. | E55: B3 先進封裝 | F55: TWD | G55: 25Q2 / 25Q3 / 25Q4 / 26Q1 / 26Q2 | H55: 150750 | I55: 168569 | J55: 177915.71 | K55: 173662.15 | L55: 191064 | M55: =IF(OR(N(H55)=0,L55=""),"",L55/H55-1) -> 0.26742289 | N55: 13201 | O55: 18469.932 | P55: 17531.793 | Q55: 21134 | R55: =IF(OR(N(L55)=0,Q55=""),"",Q55/L55) -> 0.11061215 | S55: 40150 | T55: =IF(OR(N(L55)=0,S55=""),"",S55/L55) -> 0.21013901 | U55: 21068 | V55: =IF(OR(N(L55)=0,U55=""),"",U55/L55) -> 0.11026672 | W55: 645387.71 | X55: 51534.932 | Y55: =IF(OR(N(W55)=0,X55=""),"",X55/W55) -> 0.079851121 | Z55: =IF(AA55="A","四季持續盈利",IF(AA55="B","最新季為正/波動",IF(AA55="C","虧損收窄",IF(AA55="D","虧損擴大或轉虧","數據不足")))) -> 四季持續盈利 | AA55: =IF(COUNT(N55:Q55)<4,"—",IF(MIN(N55:Q55)>0,"A",IF(Q55>0,"B",IF(Q55>N55,"C","D")))) -> A | AB55: 2026-06-30
A56: 55 | B56: ATO | C56: 燃氣公用 | D56: Atmos Energy Corporation | E56: Utilities - Regulated Gas | F56: USD | G56: 25Q2 / 25Q3 / 25Q4 / 26Q1 / 26Q2 | H56: 838.774 | I56: 737.48 | J56: 1342.585 | K56: 1962.402 | L56: 879.059 | M56: =IF(OR(N(H56)=0,L56=""),"",L56/H56-1) -> 0.048028432 | N56: 219.485 | O56: 514.764 | P56: 764.804 | Q56: 320.414 | R56: =IF(OR(N(L56)=0,Q56=""),"",Q56/L56) -> 0.36449658 | S56: 647.684 | T56: =IF(OR(N(L56)=0,S56=""),"",S56/L56) -> 0.73679241 | U56: 242.689 | V56: =IF(OR(N(L56)=0,U56=""),"",U56/L56) -> 0.27607817 | W56: 4702.755 | X56: 1559.971 | Y56: =IF(OR(N(W56)=0,X56=""),"",X56/W56) -> 0.33171428 | Z56: =IF(AA56="A","四季持續盈利",IF(AA56="B","最新季為正/波動",IF(AA56="C","虧損收窄",IF(AA56="D","虧損擴大或轉虧","數據不足")))) -> 四季持續盈利 | AA56: =IF(COUNT(N56:Q56)<4,"—",IF(MIN(N56:Q56)>0,"A",IF(Q56>0,"B",IF(Q56>N56,"C","D")))) -> A | AB56: 2026-06-30
A57: 56 | B57: AU | C57: 黃金與貴金屬礦 | D57: AngloGold Ashanti plc | E57: Gold | F57: USD | G57: 25Q2 / 25Q3 / 25Q4 / 26Q1 / 26Q2 | H57: 2445 | I57: 2417 | J57: 3068 | K57: 3236 | L57: 3104 | M57: =IF(OR(N(H57)=0,L57=""),"",L57/H57-1) -> 0.26952965 | N57: 1026 | O57: 1497 | P57: 1814 | Q57: 1583 | R57: =IF(OR(N(L57)=0,Q57=""),"",Q57/L57) -> 0.50998711 | S57: 1703 | T57: =IF(OR(N(L57)=0,S57=""),"",S57/L57) -> 0.54864691 | U57: 1002 | V57: =IF(OR(N(L57)=0,U57=""),"",U57/L57) -> 0.32280928 | W57: 9893 | X57: 4269 | Y57: =IF(OR(N(W57)=0,X57=""),"",X57/W57) -> 0.43151723 | Z57: =IF(AA57="A","四季持續盈利",IF(AA57="B","最新季為正/波動",IF(AA57="C","虧損收窄",IF(AA57="D","虧損擴大或轉虧","數據不足")))) -> 四季持續盈利 | AA57: =IF(COUNT(N57:Q57)<4,"—",IF(MIN(N57:Q57)>0,"A",IF(Q57>0,"B",IF(Q57>N57,"C","D")))) -> A | AB57: 2026-06-30
A58: 57 | B58: AVAV | C58: 國防科技與無人機 | D58: AeroVironment, Inc. | E58: Aerospace & Defense | F58: USD | G58: 25Q2 / 25Q3 / 25Q4 / 26Q1 / 26Q2 | H58: 275.05 | I58: 454.676 | J58: 472.508 | K58: 408.045 | L58: 641.616 | M58: =IF(OR(N(H58)=0,L58=""),"",L58/H58-1) -> 1.332725 | N58: -69.272 | O58: -30.224 | P58: -27.732 | Q58: 56.941 | R58: =IF(OR(N(L58)=0,Q58=""),"",Q58/L58) -> 0.088746228 | S58: 202.625 | T58: =IF(OR(N(L58)=0,S58=""),"",S58/L58) -> 0.31580416 | U58: -24.098 | V58: =IF(OR(N(L58)=0,U58=""),"",U58/L58) -> -0.03755829 | W58: 1976.845 | X58: -70.287 | Y58: =IF(OR(N(W58)=0,X58=""),"",X58/W58) -> -0.03555514 | Z58: =IF(AA58="A","四季持續盈利",IF(AA58="B","最新季為正/波動",IF(AA58="C","虧損收窄",IF(AA58="D","虧損擴大或轉虧","數據不足")))) -> 最新季為正/波動 | AA58: =IF(COUNT(N58:Q58)<4,"—",IF(MIN(N58:Q58)>0,"A",IF(Q58>0,"B",IF(Q58>N58,"C","D")))) -> B | AB58: 2026-04-30
A59: 58 | B59: AVGO | C59: AI加速晶片/GPU | D59: Broadcom Inc. | E59: A2 ASIC | F59: USD | G59: 25Q3 / 25Q4 / 26Q1 / 26Q2 / 26Q3 | H59: 15952 | I59: 18015 | J59: 19311 | K59: 22187 | M59: =IF(OR(N(H59)=0,L59=""),"",L59/H59-1) | N59: 7654 | O59: 8666 | P59: 10859 | R59: =IF(OR(N(L59)=0,Q59=""),"",Q59/L59) | T59: =IF(OR(N(L59)=0,S59=""),"",S59/L59) | V59: =IF(OR(N(L59)=0,U59=""),"",U59/L59) | W59: 63887 | X59: 26075 | Y59: =IF(OR(N(W59)=0,X59=""),"",X59/W59) -> 0.4081425 | Z59: =IF(AA59="A","四季持續盈利",IF(AA59="B","最新季為正/波動",IF(AA59="C","虧損收窄",IF(AA59="D","虧損擴大或轉虧","數據不足")))) -> 數據不足 | AA59: =IF(COUNT(N59:Q59)<4,"—",IF(MIN(N59:Q59)>0,"A",IF(Q59>0,"B",IF(Q59>N59,"C","D")))) -> — | AB59: 2026-07-31
A60: 59 | B60: AWK | C60: 水務公用 | D60: American Water Works Company, Inc. | E60: Utilities - Regulated Water | F60: USD | G60: 25Q2 / 25Q3 / 25Q4 / 26Q1 / 26Q2 | H60: 1276 | I60: 1451 | J60: 1271 | K60: 1207 | L60: 1355 | M60: =IF(OR(N(H60)=0,L60=""),"",L60/H60-1) -> 0.061912226 | N60: 614 | O60: 405 | P60: 391 | Q60: 542 | R60: =IF(OR(N(L60)=0,Q60=""),"",Q60/L60) -> 0.4 | S60: 874 | T60: =IF(OR(N(L60)=0,S60=""),"",S60/L60) -> 0.64501845 | U60: 315 | V60: =IF(OR(N(L60)=0,U60=""),"",U60/L60) -> 0.23247232 | W60: 5140 | X60: 1879 | Y60: =IF(OR(N(W60)=0,X60=""),"",X60/W60) -> 0.3655642 | Z60: =IF(AA60="A","四季持續盈利",IF(AA60="B","最新季為正/波動",IF(AA60="C","虧損收窄",IF(AA60="D","虧損擴大或轉虧","數據不足")))) -> 四季持續盈利 | AA60: =IF(COUNT(N60:Q60)<4,"—",IF(MIN(N60:Q60)>0,"A",IF(Q60>0,"B",IF(Q60>N60,"C","D")))) -> A | AB60: 2026-06-30
A61: 60 | B61: AWR | C61: 水務公用 | D61: American States Water Company | E61: Utilities - Regulated Water | F61: USD | G61: 25Q2 / 25Q3 / 25Q4 / 26Q1 / 26Q2 | H61: 163.066 | I61: 182.716 | J61: 164.278 | K61: 169.191 | L61: 181.29 | M61: =IF(OR(N(H61)=0,L61=""),"",L61/H61-1) -> 0.11175843 | N61: 61.733 | O61: 45.037 | P61: 51.371 | Q61: 63.971 | R61: =IF(OR(N(L61)=0,Q61=""),"",Q61/L61) -> 0.35286557 | S61: 137.564 | T61: =IF(OR(N(L61)=0,S61=""),"",S61/L61) -> 0.75880633 | U61: 43.274 | V61: =IF(OR(N(L61)=0,U61=""),"",U61/L61) -> 0.23870042 | W61: 658.073 | X61: 203.275 | Y61: =IF(OR(N(W61)=0,X61=""),"",X61/W61) -> 0.3088943 | Z61: =IF(AA61="A","四季持續盈利",IF(AA61="B","最新季為正/波動",IF(AA61="C","虧損收窄",IF(AA61="D","虧損擴大或轉虧","數據不足")))) -> 四季持續盈利 | AA61: =IF(COUNT(N61:Q61)<4,"—",IF(MIN(N61:Q61)>0,"A",IF(Q61>0,"B",IF(Q61>N61,"C","D")))) -> A | AB61: 2026-06-30
A62: 61 | B62: AXP | C62: 消費金融與BNPL | D62: American Express Company | E62: Credit Services | F62: USD | G62: 25Q2 / 25Q3 / 25Q4 / 26Q1 / 26Q2 | H62: 17856 | I62: 18426 | J62: 18981 | K62: 18908 | L62: 19637 | M62: =IF(OR(N(H62)=0,L62=""),"",L62/H62-1) -> 0.099742384 | R62: =IF(OR(N(L62)=0,Q62=""),"",Q62/L62) | T62: =IF(OR(N(L62)=0,S62=""),"",S62/L62) | U62: 3110 | V62: =IF(OR(N(L62)=0,U62=""),"",U62/L62) -> 0.1583745 | W62: 72230 | Y62: =IF(OR(N(W62)=0,X62=""),"",X62/W62) | Z62: =IF(AA62="A","四季持續盈利",IF(AA62="B","最新季為正/波動",IF(AA62="C","虧損收窄",IF(AA62="D","虧損擴大或轉虧","數據不足")))) -> 數據不足 | AA62: =IF(COUNT(N62:Q62)<4,"—",IF(MIN(N62:Q62)>0,"A",IF(Q62>0,"B",IF(Q62>N62,"C","D")))) -> — | AB62: 2026-06-30
A63: 62 | B63: AXTI | C63: — | D63: AXT, Inc. | E63: D9 光模塊上游 | F63: USD | G63: 25Q2 / 25Q3 / 25Q4 / 26Q1 / 26Q2 | H63: 17.974 | I63: 27.955 | J63: 23.041 | K63: 26.924 | L63: 47.589 | M63: =IF(OR(N(H63)=0,L63=""),"",L63/H63-1) -> 1.6476577 | N63: -1.123 | O63: -2.472 | P63: -1.585 | Q63: 10.423 | R63: =IF(OR(N(L63)=0,Q63=""),"",Q63/L63) -> 0.2190212 | S63: 21.366 | T63: =IF(OR(N(L63)=0,S63=""),"",S63/L63) -> 0.4489693 | U63: 11.128 | V63: =IF(OR(N(L63)=0,U63=""),"",U63/L63) -> 0.23383555 | W63: 88.326 | X63: -20.615 | Y63: =IF(OR(N(W63)=0,X63=""),"",X63/W63) -> -0.23339673 | Z63: =IF(AA63="A","四季持續盈利",IF(AA63="B","最新季為正/波動",IF(AA63="C","虧損收窄",IF(AA63="D","虧損擴大或轉虧","數據不足")))) -> 最新季為正/波動 | AA63: =IF(COUNT(N63:Q63)<4,"—",IF(MIN(N63:Q63)>0,"A",IF(Q63>0,"B",IF(Q63>N63,"C","D")))) -> B | AB63: 2026-06-30
A64: 63 | B64: BA | C64: 航太與國防 | D64: The Boeing Company | E64: Aerospace & Defense | F64: USD | G64: 25Q2 / 25Q3 / 25Q4 / 26Q1 / 26Q2 | H64: 22749 | I64: 23270 | J64: 23948 | K64: 22217 | M64: =IF(OR(N(H64)=0,L64=""),"",L64/H64-1) | N64: -4794 | O64: -815 | P64: 446 | R64: =IF(OR(N(L64)=0,Q64=""),"",Q64/L64) | T64: =IF(OR(N(L64)=0,S64=""),"",S64/L64) | V64: =IF(OR(N(L64)=0,U64=""),"",U64/L64) | W64: 89463 | X64: -5416 | Y64: =IF(OR(N(W64)=0,X64=""),"",X64/W64) -> -0.060538994 | Z64: =IF(AA64="A","四季持續盈利",IF(AA64="B","最新季為正/波動",IF(AA64="C","虧損收窄",IF(AA64="D","虧損擴大或轉虧","數據不足")))) -> 數據不足 | AA64: =IF(COUNT(N64:Q64)<4,"—",IF(MIN(N64:Q64)>0,"A",IF(Q64>0,"B",IF(Q64>N64,"C","D")))) -> — | AB64: 2026-06-30
A65: 64 | B65: BABA | C65: — | D65: Alibaba Group Holding Limited | E65: AA3 中國雲 | F65: CNY | G65: 25Q2 / 25Q3 / 25Q4 / 26Q1 / 26Q2 | H65: 247652 | I65: 247795 | J65: 284843 | K65: 243380 | L65: 268953 | M65: =IF(OR(N(H65)=0,L65=""),"",L65/H65-1) -> 0.086011823 | N65: 5365 | O65: 20160 | P65: -848 | Q65: 19619 | R65: =IF(OR(N(L65)=0,Q65=""),"",Q65/L65) -> 0.072945831 | S65: 102857 | T65: =IF(OR(N(L65)=0,S65=""),"",S65/L65) -> 0.38243485 | U65: 10614 | V65: =IF(OR(N(L65)=0,U65=""),"",U65/L65) -> 0.039464144 | W65: 1023670 | X65: 59665 | Y65: =IF(OR(N(W65)=0,X65=""),"",X65/W65) -> 0.058285385 | Z65: =IF(AA65="A","四季持續盈利",IF(AA65="B","最新季為正/波動",IF(AA65="C","虧損收窄",IF(AA65="D","虧損擴大或轉虧","數據不足")))) -> 最新季為正/波動 | AA65: =IF(COUNT(N65:Q65)<4,"—",IF(MIN(N65:Q65)>0,"A",IF(Q65>0,"B",IF(Q65>N65,"C","D")))) -> B | AB65: 2026-06-30
A66: 65 | B66: BAC | C66: 大型全能銀行 | D66: Bank of America Corporation | E66: Banks - Diversified | F66: USD | G66: 25Q2 / 25Q3 / 25Q4 / 26Q1 / 26Q2 | H66: 27443 | I66: 28088 | J66: 31180 | K66: 30272 | M66: =IF(OR(N(H66)=0,L66=""),"",L66/H66-1) | R66: =IF(OR(N(L66)=0,Q66=""),"",Q66/L66) | T66: =IF(OR(N(L66)=0,S66=""),"",S66/L66) | V66: =IF(OR(N(L66)=0,U66=""),"",U66/L66) | W66: 113097 | Y66: =IF(OR(N(W66)=0,X66=""),"",X66/W66) | Z66: =IF(AA66="A","四季持續盈利",IF(AA66="B","最新季為正/波動",IF(AA66="C","虧損收窄",IF(AA66="D","虧損擴大或轉虧","數據不足")))) -> 數據不足 | AA66: =IF(COUNT(N66:Q66)<4,"—",IF(MIN(N66:Q66)>0,"A",IF(Q66>0,"B",IF(Q66>N66,"C","D")))) -> — | AB66: 2026-06-30
A67: 66 | B67: BBY | C67: 專門零售 | D67: Best Buy Co., Inc. | E67: Specialty Retail | F67: USD | G67: 25Q3 / 25Q4 / 26Q1 / 26Q2 / 26Q3 | H67: 9438 | I67: 9672 | J67: 13814 | K67: 8936 | M67: =IF(OR(N(H67)=0,L67=""),"",L67/H67-1) | N67: 364 | O67: 693 | P67: 361 | R67: =IF(OR(N(L67)=0,Q67=""),"",Q67/L67) | T67: =IF(OR(N(L67)=0,S67=""),"",S67/L67) | V67: =IF(OR(N(L67)=0,U67=""),"",U67/L67) | W67: 41691 | X67: 1750 | Y67: =IF(OR(N(W67)=0,X67=""),"",X67/W67) -> 0.041975486 | Z67: =IF(AA67="A","四季持續盈利",IF(AA67="B","最新季為正/波動",IF(AA67="C","虧損收窄",IF(AA67="D","虧損擴大或轉虧","數據不足")))) -> 數據不足 | AA67: =IF(COUNT(N67:Q67)<4,"—",IF(MIN(N67:Q67)>0,"A",IF(Q67>0,"B",IF(Q67>N67,"C","D")))) -> — | AB67: 2026-07-31
A68: 67 | B68: BC | C68: 家居耐用與休閒用品 | D68: Brunswick Corporation | E68: Recreational Vehicles | F68: USD | G68: 25Q2 / 25Q3 / 25Q4 / 26Q1 / 26Q2 | H68: 1447 | I68: 1360.2 | J68: 1333.8 | K68: 1378.1 | L68: 1557.8 | M68: =IF(OR(N(H68)=0,L68=""),"",L68/H68-1) -> 0.076572218 | N68: 91.6 | O68: 52.1 | P68: 55.1 | Q68: 136.4 | R68: =IF(OR(N(L68)=0,Q68=""),"",Q68/L68) -> 0.087559379 | S68: 437.8 | T68: =IF(OR(N(L68)=0,S68=""),"",S68/L68) -> 0.28103736 | U68: 109.8 | V68: =IF(OR(N(L68)=0,U68=""),"",U68/L68) -> 0.070484016 | W68: 5362.8 | X68: 312.4 | Y68: =IF(OR(N(W68)=0,X68=""),"",X68/W68) -> 0.058253151 | Z68: =IF(AA68="A","四季持續盈利",IF(AA68="B","最新季為正/波動",IF(AA68="C","虧損收窄",IF(AA68="D","虧損擴大或轉虧","數據不足")))) -> 四季持續盈利 | AA68: =IF(COUNT(N68:Q68)<4,"—",IF(MIN(N68:Q68)>0,"A",IF(Q68>0,"B",IF(Q68>N68,"C","D")))) -> A | AB68: 2026-06-30
A69: 68 | B69: BE | C69: — | D69: Bloom Energy Corporation | E69: F2 散熱液冷 | F69: USD | G69: 25Q2 / 25Q3 / 25Q4 / 26Q1 / 26Q2 | H69: 401.242 | I69: 519.048 | J69: 777.683 | K69: 751.054 | L69: 1065.365 | M69: =IF(OR(N(H69)=0,L69=""),"",L69/H69-1) -> 1.6551682 | N69: 7.846 | O69: 87.529 | P69: 72.19 | Q69: 182.237 | R69: =IF(OR(N(L69)=0,Q69=""),"",Q69/L69) -> 0.17105593 | S69: 355.572 | T69: =IF(OR(N(L69)=0,S69=""),"",S69/L69) -> 0.33375604 | U69: 196.29 | V69: =IF(OR(N(L69)=0,U69=""),"",U69/L69) -> 0.18424671 | W69: 2023.994 | X69: 72.802 | Y69: =IF(OR(N(W69)=0,X69=""),"",X69/W69) -> 0.035969474 | Z69: =IF(AA69="A","四季持續盈利",IF(AA69="B","最新季為正/波動",IF(AA69="C","虧損收窄",IF(AA69="D","虧損擴大或轉虧","數據不足")))) -> 四季持續盈利 | AA69: =IF(COUNT(N69:Q69)<4,"—",IF(MIN(N69:Q69)>0,"A",IF(Q69>0,"B",IF(Q69>N69,"C","D")))) -> A | AB69: 2026-06-30
A70: 69 | B70: BEAM | C70: 基因治療與基因編輯 | D70: Beam Therapeutics Inc. | E70: Biotechnology | F70: USD | G70: 25Q2 / 25Q3 / 25Q4 / 26Q1 / 26Q2 | H70: 8.466 | I70: 9.698 | J70: 114.109 | K70: 31.738 | L70: 0.49 | M70: =IF(OR(N(H70)=0,L70=""),"",L70/H70-1) -> -0.94212143 | N70: -126.811 | O70: -17.445 | P70: -107.215 | Q70: -126.553 | R70: =IF(OR(N(L70)=0,Q70=""),"",Q70/L70) -> -258.27143 | T70: =IF(OR(N(L70)=0,S70=""),"",S70/L70) | U70: -122.678 | V70: =IF(OR(N(L70)=0,U70=""),"",U70/L70) -> -250.36327 | W70: 139.743 | X70: -383.693 | Y70: =IF(OR(N(W70)=0,X70=""),"",X70/W70) -> -2.7457046 | Z70: =IF(AA70="A","四季持續盈利",IF(AA70="B","最新季為正/波動",IF(AA70="C","虧損收窄",IF(AA70="D","虧損擴大或轉虧","數據不足")))) -> 虧損收窄 | AA70: =IF(COUNT(N70:Q70)<4,"—",IF(MIN(N70:Q70)>0,"A",IF(Q70>0,"B",IF(Q70>N70,"C","D")))) -> C | AB70: 2026-06-30
A71: 70 | B71: BEN | C71: 資產管理 | D71: Franklin Templeton Inc. | E71: Asset Management | F71: USD | G71: 25Q1 / 25Q2 / 25Q3 / 25Q4 / 26Q1 | H71: 2111.4 | I71: 2064 | J71: 2343.7 | K71: 2327.1 | L71: 2294.9 | M71: =IF(OR(N(H71)=0,L71=""),"",L71/H71-1) -> 0.08690916 | N71: 204.1 | O71: 340.9 | P71: 368.5 | Q71: 365.4 | R71: =IF(OR(N(L71)=0,Q71=""),"",Q71/L71) -> 0.15922262 | S71: 1837.2 | T71: =IF(OR(N(L71)=0,S71=""),"",S71/L71) -> 0.80055776 | U71: 268.2 | V71: =IF(OR(N(L71)=0,U71=""),"",U71/L71) -> 0.11686784 | W71: 8770.7 | X71: 1099.8 | Y71: =IF(OR(N(W71)=0,X71=""),"",X71/W71) -> 0.12539478 | Z71: =IF(AA71="A","四季持續盈利",IF(AA71="B","最新季為正/波動",IF(AA71="C","虧損收窄",IF(AA71="D","虧損擴大或轉虧","數據不足")))) -> 四季持續盈利 | AA71: =IF(COUNT(N71:Q71)<4,"—",IF(MIN(N71:Q71)>0,"A",IF(Q71>0,"B",IF(Q71>N71,"C","D")))) -> A | AB71: 2026-03-31
A72: 71 | B72: BF.B | C72: 酒精飲品 | D72: Brown-Forman Corporation | E72: Beverages - Wineries & Distilleries | F72: USD | G72: 25Q3 / 25Q4 / 26Q1 / 26Q2 / 26Q3 | H72: 924 | I72: 1036 | J72: 1056 | K72: 912 | M72: =IF(OR(N(H72)=0,L72=""),"",L72/H72-1) | N72: 309 | O72: 343 | P72: 228 | R72: =IF(OR(N(L72)=0,Q72=""),"",Q72/L72) | T72: =IF(OR(N(L72)=0,S72=""),"",S72/L72) | V72: =IF(OR(N(L72)=0,U72=""),"",U72/L72) | W72: 3928 | X72: 1152 | Y72: =IF(OR(N(W72)=0,X72=""),"",X72/W72) -> 0.29327902 | Z72: =IF(AA72="A","四季持續盈利",IF(AA72="B","最新季為正/波動",IF(AA72="C","虧損收窄",IF(AA72="D","虧損擴大或轉虧","數據不足")))) -> 數據不足 | AA72: =IF(COUNT(N72:Q72)<4,"—",IF(MIN(N72:Q72)>0,"A",IF(Q72>0,"B",IF(Q72>N72,"C","D")))) -> — | AB72: 2026-07-31
A73: 72 | B73: BG | C73: 農產品與農業投入 | D73: Bunge Global SA | E73: Farm Products | F73: USD | G73: 25Q2 / 25Q3 / 25Q4 / 26Q1 / 26Q2 | H73: 12769 | I73: 22155 | J73: 23762 | K73: 21861 | L73: 24041 | M73: =IF(OR(N(H73)=0,L73=""),"",L73/H73-1) -> 0.88276294 | N73: 385 | O73: 374 | P73: 235 | Q73: 1075 | R73: =IF(OR(N(L73)=0,Q73=""),"",Q73/L73) -> 0.044715278 | S73: 1681 | T73: =IF(OR(N(L73)=0,S73=""),"",S73/L73) -> 0.069922216 | U73: 678 | V73: =IF(OR(N(L73)=0,U73=""),"",U73/L73) -> 0.028201822 | W73: 70329 | X73: 1296 | Y73: =IF(OR(N(W73)=0,X73=""),"",X73/W73) -> 0.018427676 | Z73: =IF(AA73="A","四季持續盈利",IF(AA73="B","最新季為正/波動",IF(AA73="C","虧損收窄",IF(AA73="D","虧損擴大或轉虧","數據不足")))) -> 四季持續盈利 | AA73: =IF(COUNT(N73:Q73)<4,"—",IF(MIN(N73:Q73)>0,"A",IF(Q73>0,"B",IF(Q73>N73,"C","D")))) -> A | AB73: 2026-06-30
A74: 73 | B74: BIDU | C74: — | D74: Baidu, Inc. | E74: AA3 中國雲 | F74: CNY | G74: 25Q2 / 25Q3 / 25Q4 / 26Q1 / 26Q2 | H74: 32713 | I74: 31174 | J74: 32740 | K74: 32075 | L74: 31325 | M74: =IF(OR(N(H74)=0,L74=""),"",L74/H74-1) -> -0.042429615 | N74: 1099 | O74: 1483 | P74: 3193 | Q74: 3024 | R74: =IF(OR(N(L74)=0,Q74=""),"",Q74/L74) -> 0.096536313 | S74: 12227 | T74: =IF(OR(N(L74)=0,S74=""),"",S74/L74) -> 0.39032721 | U74: 2319 | V74: =IF(OR(N(L74)=0,U74=""),"",U74/L74) -> 0.074030327 | W74: 129079 | X74: 10367 | Y74: =IF(OR(N(W74)=0,X74=""),"",X74/W74) -> 0.080315156 | Z74: =IF(AA74="A","四季持續盈利",IF(AA74="B","最新季為正/波動",IF(AA74="C","虧損收窄",IF(AA74="D","虧損擴大或轉虧","數據不足")))) -> 四季持續盈利 | AA74: =IF(COUNT(N74:Q74)<4,"—",IF(MIN(N74:Q74)>0,"A",IF(Q74>0,"B",IF(Q74>N74,"C","D")))) -> A | AB74: 2026-06-30
A75: 74 | B75: BIIB | C75: 大型生物科技 | D75: Biogen Inc. | E75: Drug Manufacturers - General | F75: USD | G75: 25Q2 / 25Q3 / 25Q4 / 26Q1 / 26Q2 | H75: 2645.5 | I75: 2534.7 | J75: 2279.4 | K75: 2477.8 | L75: 2736 | M75: =IF(OR(N(H75)=0,L75=""),"",L75/H75-1) -> 0.034209034 | N75: 606.5 | O75: 385.5 | P75: 459.8 | Q75: 482.8 | R75: =IF(OR(N(L75)=0,Q75=""),"",Q75/L75) -> 0.17646199 | S75: 1959.1 | T75: =IF(OR(N(L75)=0,S75=""),"",S75/L75) -> 0.71604532 | U75: 97.5 | V75: =IF(OR(N(L75)=0,U75=""),"",U75/L75) -> 0.035635965 | W75: 9890.6 | X75: 2469 | Y75: =IF(OR(N(W75)=0,X75=""),"",X75/W75) -> 0.24963096 | Z75: =IF(AA75="A","四季持續盈利",IF(AA75="B","最新季為正/波動",IF(AA75="C","虧損收窄",IF(AA75="D","虧損擴大或轉虧","數據不足")))) -> 四季持續盈利 | AA75: =IF(COUNT(N75:Q75)<4,"—",IF(MIN(N75:Q75)>0,"A",IF(Q75>0,"B",IF(Q75>N75,"C","D")))) -> A | AB75: 2026-06-30
A76: 75 | B76: BJ | C76: 大賣場與超巿 | D76: BJ's Wholesale Club Holdings, Inc. | E76: Discount Stores | F76: USD | G76: 25Q3 / 25Q4 / 26Q1 / 26Q2 / 26Q3 | H76: 5380.24 | I76: 5348.163 | J76: 5575.388 | K76: 5661.5 | L76: 6226.579 | M76: =IF(OR(N(H76)=0,L76=""),"",L76/H76-1) -> 0.15730506 | N76: 226.186 | O76: 191.423 | P76: 221.891 | Q76: 258.793 | R76: =IF(OR(N(L76)=0,Q76=""),"",Q76/L76) -> 0.04156263 | S76: 1109.999 | T76: =IF(OR(N(L76)=0,S76=""),"",S76/L76) -> 0.17826787 | U76: 173.867 | V76: =IF(OR(N(L76)=0,U76=""),"",U76/L76) -> 0.027923359 | W76: 21457.274 | X76: 846.045 | Y76: =IF(OR(N(W76)=0,X76=""),"",X76/W76) -> 0.039429286 | Z76: =IF(AA76="A","四季持續盈利",IF(AA76="B","最新季為正/波動",IF(AA76="C","虧損收窄",IF(AA76="D","虧損擴大或轉虧","數據不足")))) -> 四季持續盈利 | AA76: =IF(COUNT(N76:Q76)<4,"—",IF(MIN(N76:Q76)>0,"A",IF(Q76>0,"B",IF(Q76>N76,"C","D")))) -> A | AB76: 2026-07-31
A77: 76 | B77: BKR | C77: 油田服務 | D77: Baker Hughes Company | E77: Oil & Gas Equipment & Services | F77: USD | G77: 25Q2 / 25Q3 / 25Q4 / 26Q1 / 26Q2 | H77: 6910 | I77: 7010 | J77: 7386 | K77: 6587 | L77: 6742 | M77: =IF(OR(N(H77)=0,L77=""),"",L77/H77-1) -> -0.02431259 | N77: 948 | O77: 970 | P77: 809 | Q77: 865 | R77: =IF(OR(N(L77)=0,Q77=""),"",Q77/L77) -> 0.12830021 | S77: 1577 | T77: =IF(OR(N(L77)=0,S77=""),"",S77/L77) -> 0.23390685 | U77: 681 | V77: =IF(OR(N(L77)=0,U77=""),"",U77/L77) -> 0.1010086 | W77: 27733 | X77: 3557 | Y77: =IF(OR(N(W77)=0,X77=""),"",X77/W77) -> 0.12825875 | Z77: =IF(AA77="A","四季持續盈利",IF(AA77="B","最新季為正/波動",IF(AA77="C","虧損收窄",IF(AA77="D","虧損擴大或轉虧","數據不足")))) -> 四季持續盈利 | AA77: =IF(COUNT(N77:Q77)<4,"—",IF(MIN(N77:Q77)>0,"A",IF(Q77>0,"B",IF(Q77>N77,"C","D")))) -> A | AB77: 2026-06-30
A78: 77 | B78: BLK | C78: 資產管理 | D78: BlackRock, Inc. | E78: Asset Management | F78: USD | G78: 25Q2 / 25Q3 / 25Q4 / 26Q1 / 26Q2 | H78: 5423 | I78: 6509 | J78: 7008 | K78: 6698 | L78: 7084 | M78: =IF(OR(N(H78)=0,L78=""),"",L78/H78-1) -> 0.30628803 | N78: 2045 | O78: 2228 | P78: 2261 | Q78: 2472 | R78: =IF(OR(N(L78)=0,Q78=""),"",Q78/L78) -> 0.34895539 | S78: 3468 | T78: =IF(OR(N(L78)=0,S78=""),"",S78/L78) -> 0.48955392 | U78: 1914 | V78: =IF(OR(N(L78)=0,U78=""),"",U78/L78) -> 0.27018634 | W78: 24216 | X78: 7909 | Y78: =IF(OR(N(W78)=0,X78=""),"",X78/W78) -> 0.32660225 | Z78: =IF(AA78="A","四季持續盈利",IF(AA78="B","最新季為正/波動",IF(AA78="C","虧損收窄",IF(AA78="D","虧損擴大或轉虧","數據不足")))) -> 四季持續盈利 | AA78: =IF(COUNT(N78:Q78)<4,"—",IF(MIN(N78:Q78)>0,"A",IF(Q78>0,"B",IF(Q78>N78,"C","D")))) -> A | AB78: 2026-06-30
A79: 78 | B79: BMY | C79: 大型藥廠 | D79: Bristol-Myers Squibb Company | E79: Drug Manufacturers - General | F79: USD | G79: 25Q2 / 25Q3 / 25Q4 / 26Q1 / 26Q2 | H79: 12269 | I79: 12222 | J79: 12503 | K79: 11489 | L79: 12973 | M79: =IF(OR(N(H79)=0,L79=""),"",L79/H79-1) -> 0.05738039 | N79: 3639 | O79: 2813 | P79: 3365 | Q79: 4025 | R79: =IF(OR(N(L79)=0,Q79=""),"",Q79/L79) -> 0.31025977 | S79: 9247 | T79: =IF(OR(N(L79)=0,S79=""),"",S79/L79) -> 0.7127881 | U79: 3317 | V79: =IF(OR(N(L79)=0,U79=""),"",U79/L79) -> 0.25568488 | W79: 48195 | X79: 13724 | Y79: =IF(OR(N(W79)=0,X79=""),"",X79/W79) -> 0.28475983 | Z79: =IF(AA79="A","四季持續盈利",IF(AA79="B","最新季為正/波動",IF(AA79="C","虧損收窄",IF(AA79="D","虧損擴大或轉虧","數據不足")))) -> 四季持續盈利 | AA79: =IF(COUNT(N79:Q79)<4,"—",IF(MIN(N79:Q79)>0,"A",IF(Q79>0,"B",IF(Q79>N79,"C","D")))) -> A | AB79: 2026-06-30
A80: 79 | B80: BRO | C80: 保險經紀 | D80: Brown & Brown, Inc. | E80: Insurance Brokers | F80: USD | G80: 25Q2 / 25Q3 / 25Q4 / 26Q1 / 26Q2 | H80: 1249 | I80: 1550 | J80: 1580 | K80: 1880 | L80: 1654 | M80: =IF(OR(N(H80)=0,L80=""),"",L80/H80-1) -> 0.32425941 | N80: 374 | O80: 340 | P80: 551 | Q80: 417 | R80: =IF(OR(N(L80)=0,Q80=""),"",Q80/L80) -> 0.25211608 | S80: 816 | T80: =IF(OR(N(L80)=0,S80=""),"",S80/L80) -> 0.49334946 | U80: 288 | V80: =IF(OR(N(L80)=0,U80=""),"",U80/L80) -> 0.17412334 | W80: 5763 | X80: 1502 | Y80: =IF(OR(N(W80)=0,X80=""),"",X80/W80) -> 0.26062815 | Z80: =IF(AA80="A","四季持續盈利",IF(AA80="B","最新季為正/波動",IF(AA80="C","虧損收窄",IF(AA80="D","虧損擴大或轉虧","數據不足")))) -> 四季持續盈利 | AA80: =IF(COUNT(N80:Q80)<4,"—",IF(MIN(N80:Q80)>0,"A",IF(Q80>0,"B",IF(Q80>N80,"C","D")))) -> A | AB80: 2026-06-30
A81: 80 | B81: BSX | C81: 醫療器械 | D81: Boston Scientific Corporation | E81: Medical Devices | F81: USD | G81: 25Q2 / 25Q3 / 25Q4 / 26Q1 / 26Q2 | H81: 5061 | I81: 5065 | J81: 5286 | K81: 5203 | M81: =IF(OR(N(H81)=0,L81=""),"",L81/H81-1) | N81: 1050 | O81: 1041 | P81: 1072 | R81: =IF(OR(N(L81)=0,Q81=""),"",Q81/L81) | T81: =IF(OR(N(L81)=0,S81=""),"",S81/L81) | V81: =IF(OR(N(L81)=0,U81=""),"",U81/L81) | W81: 20074 | X81: 3971 | Y81: =IF(OR(N(W81)=0,X81=""),"",X81/W81) -> 0.19781807 | Z81: =IF(AA81="A","四季持續盈利",IF(AA81="B","最新季為正/波動",IF(AA81="C","虧損收窄",IF(AA81="D","虧損擴大或轉虧","數據不足")))) -> 數據不足 | AA81: =IF(COUNT(N81:Q81)<4,"—",IF(MIN(N81:Q81)>0,"A",IF(Q81>0,"B",IF(Q81>N81,"C","D")))) -> — | AB81: 2026-06-30
A82: 81 | B82: BTU | C82: 煤炭 | D82: Peabody Energy Corporation | E82: Thermal Coal | F82: USD | G82: 25Q2 / 25Q3 / 25Q4 / 26Q1 / 26Q2 | H82: 890.1 | I82: 1012.1 | J82: 1022.3 | K82: 973.3 | L82: 1003.2 | M82: =IF(OR(N(H82)=0,L82=""),"",L82/H82-1) -> 0.12706437 | N82: -26.1 | O82: 13.6 | P82: -46.1 | Q82: -95.3 | R82: =IF(OR(N(L82)=0,Q82=""),"",Q82/L82) -> -0.094996013 | S82: 49.3 | T82: =IF(OR(N(L82)=0,S82=""),"",S82/L82) -> 0.049142743 | U82: -90.6 | V82: =IF(OR(N(L82)=0,U82=""),"",U82/L82) -> -0.090311005 | W82: 3861.5 | X82: -5 | Y82: =IF(OR(N(W82)=0,X82=""),"",X82/W82) -> -0.0012948336 | Z82: =IF(AA82="A","四季持續盈利",IF(AA82="B","最新季為正/波動",IF(AA82="C","虧損收窄",IF(AA82="D","虧損擴大或轉虧","數據不足")))) -> 虧損擴大或轉虧 | AA82: =IF(COUNT(N82:Q82)<4,"—",IF(MIN(N82:Q82)>0,"A",IF(Q82>0,"B",IF(Q82>N82,"C","D")))) -> D | AB82: 2026-06-30
A83: 82 | B83: BWXT | C83: — | D83: BWX Technologies, Inc. | E83: F3 能源 | F83: USD | G83: 25Q2 / 25Q3 / 25Q4 / 26Q1 / 26Q2 | H83: 764.039 | I83: 866.286 | J83: 885.842 | K83: 860.217 | L83: 901.625 | M83: =IF(OR(N(H83)=0,L83=""),"",L83/H83-1) -> 0.1800772 | N83: 92.134 | O83: 72.939 | P83: 85.251 | Q83: 89.706 | R83: =IF(OR(N(L83)=0,Q83=""),"",Q83/L83) -> 0.099493692 | S83: 202.305 | T83: =IF(OR(N(L83)=0,S83=""),"",S83/L83) -> 0.22437821 | U83: 89.014 | V83: =IF(OR(N(L83)=0,U83=""),"",U83/L83) -> 0.098726189 | W83: 3198.425 | X83: 324.576 | Y83: =IF(OR(N(W83)=0,X83=""),"",X83/W83) -> 0.10147995 | Z83: =IF(AA83="A","四季持續盈利",IF(AA83="B","最新季為正/波動",IF(AA83="C","虧損收窄",IF(AA83="D","虧損擴大或轉虧","數據不足")))) -> 四季持續盈利 | AA83: =IF(COUNT(N83:Q83)<4,"—",IF(MIN(N83:Q83)>0,"A",IF(Q83>0,"B",IF(Q83>N83,"C","D")))) -> A | AB83: 2026-06-30
A84: 83 | B84: BX | C84: 另類資產與私募信貸 | D84: Blackstone Inc. | E84: Asset Management | F84: USD | G84: 25Q2 / 25Q3 / 25Q4 / 26Q1 / 26Q2 | H84: 3161.236 | I84: 2685.881 | J84: 3736.455 | K84: 3002.779 | L84: 4187.932 | M84: =IF(OR(N(H84)=0,L84=""),"",L84/H84-1) -> 0.32477676 | R84: =IF(OR(N(L84)=0,Q84=""),"",Q84/L84) | T84: =IF(OR(N(L84)=0,S84=""),"",S84/L84) | U84: 1229.189 | V84: =IF(OR(N(L84)=0,U84=""),"",U84/L84) -> 0.29350739 | W84: 12410.012 | Y84: =IF(OR(N(W84)=0,X84=""),"",X84/W84) | Z84: =IF(AA84="A","四季持續盈利",IF(AA84="B","最新季為正/波動",IF(AA84="C","虧損收窄",IF(AA84="D","虧損擴大或轉虧","數據不足")))) -> 數據不足 | AA84: =IF(COUNT(N84:Q84)<4,"—",IF(MIN(N84:Q84)>0,"A",IF(Q84>0,"B",IF(Q84>N84,"C","D")))) -> — | AB84: 2026-06-30
A85: 84 | B85: BXP | C85: 辦公樓REIT | D85: BXP, Inc. | E85: REIT - Office | F85: USD | G85: 25Q2 / 25Q3 / 25Q4 / 26Q1 / 26Q2 | H85: 868.457 | I85: 871.51 | J85: 877.097 | K85: 872.148 | L85: 895.699 | M85: =IF(OR(N(H85)=0,L85=""),"",L85/H85-1) -> 0.031368277 | N85: 253.99 | O85: 254.588 | P85: 227.906 | Q85: 258.867 | R85: =IF(OR(N(L85)=0,Q85=""),"",Q85/L85) -> 0.28901115 | S85: 550.189 | T85: =IF(OR(N(L85)=0,S85=""),"",S85/L85) -> 0.61425658 | U85: 68.564 | V85: =IF(OR(N(L85)=0,U85=""),"",U85/L85) -> 0.076548037 | W85: 3482.279 | X85: 1014.351 | Y85: =IF(OR(N(W85)=0,X85=""),"",X85/W85) -> 0.29128941 | Z85: =IF(AA85="A","四季持續盈利",IF(AA85="B","最新季為正/波動",IF(AA85="C","虧損收窄",IF(AA85="D","虧損擴大或轉虧","數據不足")))) -> 四季持續盈利 | AA85: =IF(COUNT(N85:Q85)<4,"—",IF(MIN(N85:Q85)>0,"A",IF(Q85>0,"B",IF(Q85>N85,"C","D")))) -> A | AB85: 2026-06-30
A86: 85 | B86: C | C86: 大型全能銀行 | D86: Citigroup Inc. | E86: Banks - Diversified | F86: USD | G86: 25Q2 / 25Q3 / 25Q4 / 26Q1 / 26Q2 | H86: 21661 | I86: 22095 | J86: 19670 | K86: 24663 | L86: 24765 | M86: =IF(OR(N(H86)=0,L86=""),"",L86/H86-1) -> 0.14329902 | R86: =IF(OR(N(L86)=0,Q86=""),"",Q86/L86) | T86: =IF(OR(N(L86)=0,S86=""),"",S86/L86) | U86: 5831 | V86: =IF(OR(N(L86)=0,U86=""),"",U86/L86) -> 0.23545326 | W86: 85213 | Y86: =IF(OR(N(W86)=0,X86=""),"",X86/W86) | Z86: =IF(AA86="A","四季持續盈利",IF(AA86="B","最新季為正/波動",IF(AA86="C","虧損收窄",IF(AA86="D","虧損擴大或轉虧","數據不足")))) -> 數據不足 | AA86: =IF(COUNT(N86:Q86)<4,"—",IF(MIN(N86:Q86)>0,"A",IF(Q86>0,"B",IF(Q86>N86,"C","D")))) -> — | AB86: 2026-06-30
A87: 86 | B87: CAG | C87: 食品加工 | D87: Conagra Brands, Inc. | E87: Packaged Foods | F87: USD | G87: 25Q2 / 25Q3 / 25Q4 / 26Q1 / 26Q2 | H87: 2781.8 | I87: 2632.6 | J87: 2979.1 | K87: 2787.8 | L87: 2882.1 | M87: =IF(OR(N(H87)=0,L87=""),"",L87/H87-1) -> 0.036055791 | N87: 305 | O87: 370.9 | P87: 280.1 | Q87: 303 | R87: =IF(OR(N(L87)=0,Q87=""),"",Q87/L87) -> 0.10513167 | S87: 704.1 | T87: =IF(OR(N(L87)=0,S87=""),"",S87/L87) -> 0.24430103 | U87: -1616.9 | V87: =IF(OR(N(L87)=0,U87=""),"",U87/L87) -> -0.56101454 | W87: 11281.6 | X87: 1259 | Y87: =IF(OR(N(W87)=0,X87=""),"",X87/W87) -> 0.11159765 | Z87: =IF(AA87="A","四季持續盈利",IF(AA87="B","最新季為正/波動",IF(AA87="C","虧損收窄",IF(AA87="D","虧損擴大或轉虧","數據不足")))) -> 四季持續盈利 | AA87: =IF(COUNT(N87:Q87)<4,"—",IF(MIN(N87:Q87)>0,"A",IF(Q87>0,"B",IF(Q87>N87,"C","D")))) -> A | AB87: 2026-05-31
A88: 87 | B88: CAH | C88: 藥品分銷與藥房 | D88: Cardinal Health, Inc. | E88: Medical Distribution | F88: USD | G88: 25Q2 / 25Q3 / 25Q4 / 26Q1 / 26Q2 | H88: 60159 | I88: 64009 | J88: 65627 | K88: 60940 | L88: 63672 | M88: =IF(OR(N(H88)=0,L88=""),"",L88/H88-1) -> 0.058395253 | N88: 754 | O88: 763 | P88: 842 | Q88: 814 | R88: =IF(OR(N(L88)=0,Q88=""),"",Q88/L88) -> 0.012784269 | S88: 2560 | T88: =IF(OR(N(L88)=0,S88=""),"",S88/L88) -> 0.040206056 | U88: 398 | V88: =IF(OR(N(L88)=0,U88=""),"",U88/L88) -> 0.0062507853 | W88: 254248 | X88: 3173 | Y88: =IF(OR(N(W88)=0,X88=""),"",X88/W88) -> 0.012479941 | Z88: =IF(AA88="A","四季持續盈利",IF(AA88="B","最新季為正/波動",IF(AA88="C","虧損收窄",IF(AA88="D","虧損擴大或轉虧","數據不足")))) -> 四季持續盈利 | AA88: =IF(COUNT(N88:Q88)<4,"—",IF(MIN(N88:Q88)>0,"A",IF(Q88>0,"B",IF(Q88>N88,"C","D")))) -> A | AB88: 2026-06-30
A89: 88 | B89: CAMT | C89: — | D89: Camtek Ltd. | E89: B3 先進封裝 | F89: USD | G89: 25Q2 / 25Q3 / 25Q4 / 26Q1 / 26Q2 | H89: 123.317 | I89: 125.993 | J89: 128.124 | K89: 121.659 | L89: 133.243 | M89: =IF(OR(N(H89)=0,L89=""),"",L89/H89-1) -> 0.080491741 | N89: 31.845 | O89: 31.684 | P89: 27.266 | Q89: 27.227 | R89: =IF(OR(N(L89)=0,Q89=""),"",Q89/L89) -> 0.20434094 | S89: 66.702 | T89: =IF(OR(N(L89)=0,S89=""),"",S89/L89) -> 0.50060416 | U89: 23.305 | V89: =IF(OR(N(L89)=0,U89=""),"",U89/L89) -> 0.174906 | W89: 496.072 | X89: 128.203 | Y89: =IF(OR(N(W89)=0,X89=""),"",X89/W89) -> 0.25843628 | Z89: =IF(AA89="A","四季持續盈利",IF(AA89="B","最新季為正/波動",IF(AA89="C","虧損收窄",IF(AA89="D","虧損擴大或轉虧","數據不足")))) -> 四季持續盈利 | AA89: =IF(COUNT(N89:Q89)<4,"—",IF(MIN(N89:Q89)>0,"A",IF(Q89>0,"B",IF(Q89>N89,"C","D")))) -> A | AB89: 2026-06-30
A90: 89 | B90: CARR | C90: 樓宇產品與HVAC | D90: Carrier Global Corporation | E90: Building Products & Equipment | F90: USD | G90: 25Q2 / 25Q3 / 25Q4 / 26Q1 / 26Q2 | H90: 6113 | I90: 5579 | J90: 4837 | K90: 5341 | L90: 6351 | M90: =IF(OR(N(H90)=0,L90=""),"",L90/H90-1) -> 0.038933421 | N90: 495 | O90: 54 | P90: 240 | Q90: 770 | R90: =IF(OR(N(L90)=0,Q90=""),"",Q90/L90) -> 0.12124075 | S90: 1728 | T90: =IF(OR(N(L90)=0,S90=""),"",S90/L90) -> 0.27208314 | U90: 501 | V90: =IF(OR(N(L90)=0,U90=""),"",U90/L90) -> 0.078885215 | W90: 21747 | X90: 1907 | Y90: =IF(OR(N(W90)=0,X90=""),"",X90/W90) -> 0.087690256 | Z90: =IF(AA90="A","四季持續盈利",IF(AA90="B","最新季為正/波動",IF(AA90="C","虧損收窄",IF(AA90="D","虧損擴大或轉虧","數據不足")))) -> 四季持續盈利 | AA90: =IF(COUNT(N90:Q90)<4,"—",IF(MIN(N90:Q90)>0,"A",IF(Q90>0,"B",IF(Q90>N90,"C","D")))) -> A | AB90: 2026-06-30
A91: 90 | B91: CAT | C91: 機械與重工 | D91: Caterpillar Inc. | E91: Farm & Heavy Construction Machinery | F91: USD | G91: 25Q2 / 25Q3 / 25Q4 / 26Q1 / 26Q2 | H91: 16569 | I91: 17638 | J91: 19133 | K91: 17415 | L91: 20543 | M91: =IF(OR(N(H91)=0,L91=""),"",L91/H91-1) -> 0.23984549 | N91: 3052 | O91: 2660 | P91: 3085 | Q91: 4295 | R91: =IF(OR(N(L91)=0,Q91=""),"",Q91/L91) -> 0.20907365 | S91: 7400 | T91: =IF(OR(N(L91)=0,S91=""),"",S91/L91) -> 0.36022003 | U91: 3593 | V91: =IF(OR(N(L91)=0,U91=""),"",U91/L91) -> 0.17490143 | W91: 67589 | X91: 11151 | Y91: =IF(OR(N(W91)=0,X91=""),"",X91/W91) -> 0.16498247 | Z91: =IF(AA91="A","四季持續盈利",IF(AA91="B","最新季為正/波動",IF(AA91="C","虧損收窄",IF(AA91="D","虧損擴大或轉虧","數據不足")))) -> 四季持續盈利 | AA91: =IF(COUNT(N91:Q91)<4,"—",IF(MIN(N91:Q91)>0,"A",IF(Q91>0,"B",IF(Q91>N91,"C","D")))) -> A | AB91: 2026-06-30
A92: 91 | B92: CB | C92: 產險與再保 | D92: Chubb Limited | E92: Insurance - Property & Casualty | F92: USD | G92: 25Q2 / 25Q3 / 25Q4 / 26Q1 / 26Q2 | H92: 14881 | I92: 16200 | J92: 15303 | K92: 14815 | L92: 15959 | M92: =IF(OR(N(H92)=0,L92=""),"",L92/H92-1) -> 0.072441368 | N92: 4091 | O92: 3975 | P92: 3191 | Q92: 3824 | R92: =IF(OR(N(L92)=0,Q92=""),"",Q92/L92) -> 0.23961401 | T92: =IF(OR(N(L92)=0,S92=""),"",S92/L92) | U92: 2854 | V92: =IF(OR(N(L92)=0,U92=""),"",U92/L92) -> 0.17883326 | W92: 59783 | X92: 13808 | Y92: =IF(OR(N(W92)=0,X92=""),"",X92/W92) -> 0.23096867 | Z92: =IF(AA92="A","四季持續盈利",IF(AA92="B","最新季為正/波動",IF(AA92="C","虧損收窄",IF(AA92="D","虧損擴大或轉虧","數據不足")))) -> 四季持續盈利 | AA92: =IF(COUNT(N92:Q92)<4,"—",IF(MIN(N92:Q92)>0,"A",IF(Q92>0,"B",IF(Q92>N92,"C","D")))) -> A | AB92: 2026-06-30
A93: 92 | B93: CBOE | C93: 交易所與金融數據 | D93: Cboe Global Markets, Inc. | E93: Financial Data & Stock Exchanges | F93: USD | G93: 25Q2 / 25Q3 / 25Q4 / 26Q1 / 26Q2 | H93: 1173.5 | I93: 1141.7 | J93: 1204 | K93: 1272.8 | L93: 1442.8 | M93: =IF(OR(N(H93)=0,L93=""),"",L93/H93-1) -> 0.22948445 | N93: 375 | O93: 428.8 | P93: 505.6 | Q93: 476 | R93: =IF(OR(N(L93)=0,Q93=""),"",Q93/L93) -> 0.32991406 | S93: 576.9 | T93: =IF(OR(N(L93)=0,S93=""),"",S93/L93) -> 0.39984752 | U93: 353.1 | V93: =IF(OR(N(L93)=0,U93=""),"",U93/L93) -> 0.24473246 | W93: 4714.2 | X93: 1514.1 | Y93: =IF(OR(N(W93)=0,X93=""),"",X93/W93) -> 0.32117857 | Z93: =IF(AA93="A","四季持續盈利",IF(AA93="B","最新季為正/波動",IF(AA93="C","虧損收窄",IF(AA93="D","虧損擴大或轉虧","數據不足")))) -> 四季持續盈利 | AA93: =IF(COUNT(N93:Q93)<4,"—",IF(MIN(N93:Q93)>0,"A",IF(Q93>0,"B",IF(Q93>N93,"C","D")))) -> A | AB93: 2026-06-30
A94: 93 | B94: CBRE | C94: 地產開發與服務 | D94: CBRE Group, Inc. | E94: Real Estate Services | F94: USD | G94: 25Q2 / 25Q3 / 25Q4 / 26Q1 / 26Q2 | H94: 9717 | I94: 10258 | J94: 11629 | K94: 10527 | L94: 11226 | M94: =IF(OR(N(H94)=0,L94=""),"",L94/H94-1) -> 0.15529484 | N94: 445 | O94: 218 | P94: 210 | Q94: 360 | R94: =IF(OR(N(L94)=0,Q94=""),"",Q94/L94) -> 0.032068413 | S94: 2086 | T94: =IF(OR(N(L94)=0,S94=""),"",S94/L94) -> 0.18581864 | U94: 204 | V94: =IF(OR(N(L94)=0,U94=""),"",U94/L94) -> 0.0181721 | W94: 40550 | X94: 1294 | Y94: =IF(OR(N(W94)=0,X94=""),"",X94/W94) -> 0.031911221 | Z94: =IF(AA94="A","四季持續盈利",IF(AA94="B","最新季為正/波動",IF(AA94="C","虧損收窄",IF(AA94="D","虧損擴大或轉虧","數據不足")))) -> 四季持續盈利 | AA94: =IF(COUNT(N94:Q94)<4,"—",IF(MIN(N94:Q94)>0,"A",IF(Q94>0,"B",IF(Q94>N94,"C","D")))) -> A | AB94: 2026-06-30
A95: 94 | B95: CCI | C95: 通訊塔REIT | D95: Crown Castle Inc. | E95: REIT - Specialty | F95: USD | G95: 25Q2 / 25Q3 / 25Q4 / 26Q1 / 26Q2 | H95: 1060 | I95: 1072 | J95: 1071 | K95: 1010 | L95: 1008 | M95: =IF(OR(N(H95)=0,L95=""),"",L95/H95-1) -> -0.049056604 | N95: 528 | O95: 527 | P95: 482 | Q95: 472 | R95: =IF(OR(N(L95)=0,Q95=""),"",Q95/L95) -> 0.46825397 | S95: 740 | T95: =IF(OR(N(L95)=0,S95=""),"",S95/L95) -> 0.73412698 | U95: 94 | V95: =IF(OR(N(L95)=0,U95=""),"",U95/L95) -> 0.093253968 | W95: 4264 | X95: 2086 | Y95: =IF(OR(N(W95)=0,X95=""),"",X95/W95) -> 0.48921201 | Z95: =IF(AA95="A","四季持續盈利",IF(AA95="B","最新季為正/波動",IF(AA95="C","虧損收窄",IF(AA95="D","虧損擴大或轉虧","數據不足")))) -> 四季持續盈利 | AA95: =IF(COUNT(N95:Q95)<4,"—",IF(MIN(N95:Q95)>0,"A",IF(Q95>0,"B",IF(Q95>N95,"C","D")))) -> A | AB95: 2026-06-30
A96: 95 | B96: CCJ | C96: 鈾與核燃料 | D96: Cameco Corporation | E96: F3 能源 | F96: CAD | G96: 25Q1 / 25Q2 / 25Q3 / 25Q4 / 26Q1 | H96: 789.432 | I96: 877.016 | J96: 614.555 | K96: 1200.93 | L96: 845.365 | M96: =IF(OR(N(H96)=0,L96=""),"",L96/H96-1) -> 0.070852208 | N96: 156.26 | O96: 82.511 | P96: 204.322 | Q96: 164.148 | R96: =IF(OR(N(L96)=0,Q96=""),"",Q96/L96) -> 0.19417411 | S96: 301.584 | T96: =IF(OR(N(L96)=0,S96=""),"",S96/L96) -> 0.35675004 | U96: 130.751 | V96: =IF(OR(N(L96)=0,U96=""),"",U96/L96) -> 0.1546681 | W96: 3481.933 | X96: 621.259 | Y96: =IF(OR(N(W96)=0,X96=""),"",X96/W96) -> 0.17842359 | Z96: =IF(AA96="A","四季持續盈利",IF(AA96="B","最新季為正/波動",IF(AA96="C","虧損收窄",IF(AA96="D","虧損擴大或轉虧","數據不足")))) -> 四季持續盈利 | AA96: =IF(COUNT(N96:Q96)<4,"—",IF(MIN(N96:Q96)>0,"A",IF(Q96>0,"B",IF(Q96>N96,"C","D")))) -> A | AB96: 2026-03-31
A97: 96 | B97: CCL | C97: 酒店與郵輪 | D97: Carnival Corporation Ltd. | E97: Travel Services | F97: USD | G97: 25Q2 / 25Q3 / 25Q4 / 26Q1 / 26Q2 | H97: 6328 | I97: 8153 | J97: 6330 | K97: 6165 | L97: 6663 | M97: =IF(OR(N(H97)=0,L97=""),"",L97/H97-1) -> 0.052939317 | N97: 2272 | O97: 735 | P97: 606 | Q97: 852 | R97: =IF(OR(N(L97)=0,Q97=""),"",Q97/L97) -> 0.12787033 | S97: 2438 | T97: =IF(OR(N(L97)=0,S97=""),"",S97/L97) -> 0.36590125 | U97: 537 | V97: =IF(OR(N(L97)=0,U97=""),"",U97/L97) -> 0.080594327 | W97: 26621 | X97: 4482 | Y97: =IF(OR(N(W97)=0,X97=""),"",X97/W97) -> 0.16836332 | Z97: =IF(AA97="A","四季持續盈利",IF(AA97="B","最新季為正/波動",IF(AA97="C","虧損收窄",IF(AA97="D","虧損擴大或轉虧","數據不足")))) -> 四季持續盈利 | AA97: =IF(COUNT(N97:Q97)<4,"—",IF(MIN(N97:Q97)>0,"A",IF(Q97>0,"B",IF(Q97>N97,"C","D")))) -> A | AB97: 2026-05-31
A98: 97 | B98: CDE | C98: 白銀礦 | D98: Coeur Mining, Inc. | E98: Gold | F98: USD | G98: 25Q2 / 25Q3 / 25Q4 / 26Q1 / 26Q2 | H98: 480.65 | I98: 554.567 | J98: 674.847 | K98: 856.192 | L98: 1085.592 | M98: =IF(OR(N(H98)=0,L98=""),"",L98/H98-1) -> 1.2585915 | N98: 187.942 | O98: 366.113 | P98: 374.158 | Q98: 216.983 | R98: =IF(OR(N(L98)=0,Q98=""),"",Q98/L98) -> 0.19987528 | S98: 279.86 | T98: =IF(OR(N(L98)=0,S98=""),"",S98/L98) -> 0.25779483 | U98: 121.853 | V98: =IF(OR(N(L98)=0,U98=""),"",U98/L98) -> 0.11224567 | W98: 2070.126 | X98: 776.801 | Y98: =IF(OR(N(W98)=0,X98=""),"",X98/W98) -> 0.37524334 | Z98: =IF(AA98="A","四季持續盈利",IF(AA98="B","最新季為正/波動",IF(AA98="C","虧損收窄",IF(AA98="D","虧損擴大或轉虧","數據不足")))) -> 四季持續盈利 | AA98: =IF(COUNT(N98:Q98)<4,"—",IF(MIN(N98:Q98)>0,"A",IF(Q98>0,"B",IF(Q98>N98,"C","D")))) -> A | AB98: 2026-06-30
A99: 98 | B99: CDNS | C99: EDA與半導體IP | D99: Cadence Design Systems, Inc. | E99: B5 EDA | F99: USD | G99: 25Q2 / 25Q3 / 25Q4 / 26Q1 / 26Q2 | H99: 1275.441 | I99: 1338.838 | J99: 1440.114 | K99: 1474.22 | L99: 1584.451 | M99: =IF(OR(N(H99)=0,L99=""),"",L99/H99-1) -> 0.24227698 | N99: 452.786 | O99: 465.225 | P99: 431.336 | Q99: 449.963 | R99: =IF(OR(N(L99)=0,Q99=""),"",Q99/L99) -> 0.28398669 | S99: 1345.133 | T99: =IF(OR(N(L99)=0,S99=""),"",S99/L99) -> 0.84895841 | U99: 367.076 | V99: =IF(OR(N(L99)=0,U99=""),"",U99/L99) -> 0.23167394 | W99: 5296.759 | X99: 1649.781 | Y99: =IF(OR(N(W99)=0,X99=""),"",X99/W99) -> 0.3114699 | Z99: =IF(AA99="A","四季持續盈利",IF(AA99="B","最新季為正/波動",IF(AA99="C","虧損收窄",IF(AA99="D","虧損擴大或轉虧","數據不足")))) -> 四季持續盈利 | AA99: =IF(COUNT(N99:Q99)<4,"—",IF(MIN(N99:Q99)>0,"A",IF(Q99>0,"B",IF(Q99>N99,"C","D")))) -> A | AB99: 2026-06-30
A100: 99 | B100: CEG | C100: IPP與電力交易商 | D100: Constellation Energy Corporation | E100: F3 能源 | F100: USD | G100: 25Q2 / 25Q3 / 25Q4 / 26Q1 / 26Q2 | H100: 6101 | I100: 6570 | J100: 6074 | K100: 11122 | L100: 7504 | M100: =IF(OR(N(H100)=0,L100=""),"",L100/H100-1) -> 0.2299623 | N100: 1459 | O100: 806 | P100: 2266 | Q100: -47 | R100: =IF(OR(N(L100)=0,Q100=""),"",Q100/L100) -> -0.0062633262 | S100: 1228 | T100: =IF(OR(N(L100)=0,S100=""),"",S100/L100) -> 0.16364606 | U100: 513 | V100: =IF(OR(N(L100)=0,U100=""),"",U100/L100) -> 0.068363539 | W100: 25533 | X100: 4198 | Y100: =IF(OR(N(W100)=0,X100=""),"",X100/W100) -> 0.16441468 | Z100: =IF(AA100="A","四季持續盈利",IF(AA100="B","最新季為正/波動",IF(AA100="C","虧損收窄",IF(AA100="D","虧損擴大或轉虧","數據不足")))) -> 虧損擴大或轉虧 | AA100: =IF(COUNT(N100:Q100)<4,"—",IF(MIN(N100:Q100)>0,"A",IF(Q100>0,"B",IF(Q100>N100,"C","D")))) -> D | AB100: 2026-06-30
...

Sheet 明細對照
A1: 類別 | B1: 群組 | C1: Ticker | D1: 幣別 | E1: 營收 Q0 (百萬美元, 只計美元呈報) | F1: 營業利益 Q0 (百萬美元, 只計美元呈報)
A2: 子板塊 | B2: 診斷與生命科學工具 | C2: A | D2: =IFERROR(INDEX(觀察名單!$F$2:$F$533,MATCH($C2,觀察名單!$B$2:$B$533,0)),"") -> USD | E2: =IF($D2<>"USD","",IFERROR(INDEX(觀察名單!$L$2:$L$533,MATCH($C2,觀察名單!$B$2:$B$533,0)),"")) -> 1878 | F2: =IF($D2<>"USD","",IFERROR(INDEX(觀察名單!$Q$2:$Q$533,MATCH($C2,觀察名單!$B$2:$B$533,0)),"")) -> 444
A3: 子板塊 | B3: 鋁業 | C3: AA | D3: =IFERROR(INDEX(觀察名單!$F$2:$F$533,MATCH($C3,觀察名單!$B$2:$B$533,0)),"") -> USD | E3: =IF($D3<>"USD","",IFERROR(INDEX(觀察名單!$L$2:$L$533,MATCH($C3,觀察名單!$B$2:$B$533,0)),"")) -> 3966 | F3: =IF($D3<>"USD","",IFERROR(INDEX(觀察名單!$Q$2:$Q$533,MATCH($C3,觀察名單!$B$2:$B$533,0)),"")) -> 714
A4: 子板塊 | B4: 航空公司 | C4: AAL | D4: =IFERROR(INDEX(觀察名單!$F$2:$F$533,MATCH($C4,觀察名單!$B$2:$B$533,0)),"") -> USD | E4: =IF($D4<>"USD","",IFERROR(INDEX(觀察名單!$L$2:$L$533,MATCH($C4,觀察名單!$B$2:$B$533,0)),"")) -> 16735 | F4: =IF($D4<>"USD","",IFERROR(INDEX(觀察名單!$Q$2:$Q$533,MATCH($C4,觀察名單!$B$2:$B$533,0)),"")) -> 453
A5: 子板塊 | B5: 光通訊/CPO | C5: AAOI | D5: =IFERROR(INDEX(觀察名單!$F$2:$F$533,MATCH($C5,觀察名單!$B$2:$B$533,0)),"") -> USD | E5: =IF($D5<>"USD","",IFERROR(INDEX(觀察名單!$L$2:$L$533,MATCH($C5,觀察名單!$B$2:$B$533,0)),"")) -> 191.922 | F5: =IF($D5<>"USD","",IFERROR(INDEX(觀察名單!$Q$2:$Q$533,MATCH($C5,觀察名單!$B$2:$B$533,0)),"")) -> -23.847
A6: 子板塊 | B6: 樓宇產品與HVAC | C6: AAON | D6: =IFERROR(INDEX(觀察名單!$F$2:$F$533,MATCH($C6,觀察名單!$B$2:$B$533,0)),"") -> USD | E6: =IF($D6<>"USD","",IFERROR(INDEX(觀察名單!$L$2:$L$533,MATCH($C6,觀察名單!$B$2:$B$533,0)),"")) -> 626.976 | F6: =IF($D6<>"USD","",IFERROR(INDEX(觀察名單!$Q$2:$Q$533,MATCH($C6,觀察名單!$B$2:$B$533,0)),"")) -> 70.332
A7: 子板塊 | B7: 電子硬件與EMS/連接器 | C7: AAPL | D7: =IFERROR(INDEX(觀察名單!$F$2:$F$533,MATCH($C7,觀察名單!$B$2:$B$533,0)),"") -> USD | E7: =IF($D7<>"USD","",IFERROR(INDEX(觀察名單!$L$2:$L$533,MATCH($C7,觀察名單!$B$2:$B$533,0)),"")) -> 109417 | F7: =IF($D7<>"USD","",IFERROR(INDEX(觀察名單!$Q$2:$Q$533,MATCH($C7,觀察名單!$B$2:$B$533,0)),"")) -> 35695
A8: 子板塊 | B8: 大型藥廠 | C8: ABBV | D8: =IFERROR(INDEX(觀察名單!$F$2:$F$533,MATCH($C8,觀察名單!$B$2:$B$533,0)),"") -> USD | E8: =IF($D8<>"USD","",IFERROR(INDEX(觀察名單!$L$2:$L$533,MATCH($C8,觀察名單!$B$2:$B$533,0)),"")) -> 16990 | F8: =IF($D8<>"USD","",IFERROR(INDEX(觀察名單!$Q$2:$Q$533,MATCH($C8,觀察名單!$B$2:$B$533,0)),"")) -> 6723
A9: 子板塊 | B9: 醫療器械 | C9: ABT | D9: =IFERROR(INDEX(觀察名單!$F$2:$F$533,MATCH($C9,觀察名單!$B$2:$B$533,0)),"") -> USD | E9: =IF($D9<>"USD","",IFERROR(INDEX(觀察名單!$L$2:$L$533,MATCH($C9,觀察名單!$B$2:$B$533,0)),"")) | F9: =IF($D9<>"USD","",IFERROR(INDEX(觀察名單!$Q$2:$Q$533,MATCH($C9,觀察名單!$B$2:$B$533,0)),""))
A10: 子板塊 | B10: 大賣場與超巿 | C10: ACI | D10: =IFERROR(INDEX(觀察名單!$F$2:$F$533,MATCH($C10,觀察名單!$B$2:$B$533,0)),"") -> USD | E10: =IF($D10<>"USD","",IFERROR(INDEX(觀察名單!$L$2:$L$533,MATCH($C10,觀察名單!$B$2:$B$533,0)),"")) -> 24941.6 | F10: =IF($D10<>"USD","",IFERROR(INDEX(觀察名單!$Q$2:$Q$533,MATCH($C10,觀察名單!$B$2:$B$533,0)),"")) -> 258.9
A11: 子板塊 | B11: 工程建設/EPC | C11: ACM | D11: =IFERROR(INDEX(觀察名單!$F$2:$F$533,MATCH($C11,觀察名單!$B$2:$B$533,0)),"") -> USD | E11: =IF($D11<>"USD","",IFERROR(INDEX(觀察名單!$L$2:$L$533,MATCH($C11,觀察名單!$B$2:$B$533,0)),"")) -> 3586.067 | F11: =IF($D11<>"USD","",IFERROR(INDEX(觀察名單!$Q$2:$Q$533,MATCH($C11,觀察名單!$B$2:$B$533,0)),"")) -> -68.41
A12: 子板塊 | B12: IT服務與系統整合 | C12: ACN | D12: =IFERROR(INDEX(觀察名單!$F$2:$F$533,MATCH($C12,觀察名單!$B$2:$B$533,0)),"") -> USD | E12: =IF($D12<>"USD","",IFERROR(INDEX(觀察名單!$L$2:$L$533,MATCH($C12,觀察名單!$B$2:$B$533,0)),"")) -> 18718.144 | F12: =IF($D12<>"USD","",IFERROR(INDEX(觀察名單!$Q$2:$Q$533,MATCH($C12,觀察名單!$B$2:$B$533,0)),"")) -> 3175.298
A13: 子板塊 | B13: 企業軟體/SaaS | C13: ADBE | D13: =IFERROR(INDEX(觀察名單!$F$2:$F$533,MATCH($C13,觀察名單!$B$2:$B$533,0)),"") -> USD | E13: =IF($D13<>"USD","",IFERROR(INDEX(觀察名單!$L$2:$L$533,MATCH($C13,觀察名單!$B$2:$B$533,0)),"")) -> 6618 | F13: =IF($D13<>"USD","",IFERROR(INDEX(觀察名單!$Q$2:$Q$533,MATCH($C13,觀察名單!$B$2:$B$533,0)),"")) -> 2238
... A610: AI 小群組 | B610: C2 NAND | C610: WDC | D610: =IFERROR(INDEX(觀察名單!$F$2:$F$533,MATCH($C610,觀察名單!$B$2:$B$533,0)),"") -> USD | E610: =IF($D610<>"USD","",IFERROR(INDEX(觀察名單!$L$2:$L$533,MATCH($C610,觀察名單!$B$2:$B$533,0)),"")) -> 3747 | F610: =IF($D610<>"USD","",IFERROR(INDEX(觀察名單!$Q$2:$Q$533,MATCH($C610,觀察名單!$B$2:$B$533,0)),"")) -> 1606

Sheet 子板塊彙總
A1: # | B1: 群組 | C1: 成分股數 | D1: 營收 Q0 合計 (百萬美元) | E1: 營業利益 Q0 合計 (百萬美元) | F1: 合計營業利益率 % | G1: 盈利成分股數 (營業利益 > 0) | H1: 非美元呈報 (不計入合計) | I1: R4.00 5日資金流向 z | J1: 成分股
A2: 1 | B2: IPP與電力交易商 | C2: 4 | D2: =SUMIFS(明細對照!$E$2:$E$610,明細對照!$A$2:$A$610,"子板塊",明細對照!$B$2:$B$610,$B2) -> 19961 | E2: =SUMIFS(明細對照!$F$2:$F$610,明細對照!$A$2:$A$610,"子板塊",明細對照!$B$2:$B$610,$B2) -> 1600 | F2: =IF(N(D2)=0,"",E2/D2) -> 0.080156305 | G2: =COUNTIFS(明細對照!$A$2:$A$610,"子板塊",明細對照!$B$2:$B$610,$B2,明細對照!$F$2:$F$610,">0") -> 3 | H2: =COUNTIFS(明細對照!$A$2:$A$610,"子板塊",明細對照!$B$2:$B$610,$B2)-COUNTIFS(明細對照!$A$2:$A$610,"子板塊",明細對照!$B$2:$B$610,$B2,明細對照!$D$2:$D$610,"USD") -> 0 | I2: 1.09 | J2: CEG、VST、NRG、TLN
A3: 2 | B3: 記憶體/HBM | C3: 4 | D3: =SUMIFS(明細對照!$E$2:$E$610,明細對照!$A$2:$A$610,"子板塊",明細對照!$B$2:$B$610,$B3) -> 57797 | E3: =SUMIFS(明細對照!$F$2:$F$610,明細對照!$A$2:$A$610,"子板塊",明細對照!$B$2:$B$610,$B3) -> 43524 | F3: =IF(N(D3)=0,"",E3/D3) -> 0.75304947 | G3: =COUNTIFS(明細對照!$A$2:$A$610,"子板塊",明細對照!$B$2:$B$610,$B3,明細對照!$F$2:$F$610,">0") -> 4 | H3: =COUNTIFS(明細對照!$A$2:$A$610,"子板塊",明細對照!$B$2:$B$610,$B3)-COUNTIFS(明細對照!$A$2:$A$610,"子板塊",明細對照!$B$2:$B$610,$B3,明細對照!$D$2:$D$610,"USD") -> 0 | I3: 0.98 | J3: MU、WDC、SNDK、STX
A4: 3 | B4: 數位資產金融與礦業轉HPC | C4: 6 | D4: =SUMIFS(明細對照!$E$2:$E$610,明細對照!$A$2:$A$610,"子板塊",明細對照!$B$2:$B$610,$B4) -> 3715.724 | E4: =SUMIFS(明細對照!$F$2:$F$610,明細對照!$A$2:$A$610,"子板塊",明細對照!$B$2:$B$610,$B4) -> 41.208 | F4: =IF(N(D4)=0,"",E4/D4) -> 0.011090167 | G4: =COUNTIFS(明細對照!$A$2:$A$610,"子板塊",明細對照!$B$2:$B$610,$B4,明細對照!$F$2:$F$610,">0") -> 2 | H4: =COUNTIFS(明細對照!$A$2:$A$610,"子板塊",明細對照!$B$2:$B$610,$B4)-COUNTIFS(明細對照!$A$2:$A$610,"子板塊",明細對照!$B$2:$B$610,$B4,明細對照!$D$2:$D$610,"USD") -> 0 | I4: 0.91 | J4: COIN、HOOD、CRCL、MARA、RIOT、IREN
A5: 4 | B5: 晶圓代工/IDM | C5: 4 | D5: =SUMIFS(明細對照!$E$2:$E$610,明細對照!$A$2:$A$610,"子板塊",明細對照!$B$2:$B$610,$B5) -> 17914 | E5: =SUMIFS(明細對照!$F$2:$F$610,明細對照!$A$2:$A$610,"子板塊",明細對照!$B$2:$B$610,$B5) -> 2140 | F5: =IF(N(D5)=0,"",E5/D5) -> 0.11945964 | G5: =COUNTIFS(明細對照!$A$2:$A$610,"子板塊",明細對照!$B$2:$B$610,$B5,明細對照!$F$2:$F$610,">0") -> 2 | H5: =COUNTIFS(明細對照!$A$2:$A$610,"子板塊",明細對照!$B$2:$B$610,$B5)-COUNTIFS(明細對照!$A$2:$A$610,"子板塊",明細對照!$B$2:$B$610,$B5,明細對照!$D$2:$D$610,"USD") -> 2 | I5: 0.9 | J5: TSM、INTC、GFS、UMC
A6: 5 | B6: 傳統汽車與零部件 | C6: 5 | D6: =SUMIFS(明細對照!$E$2:$E$610,明細對照!$A$2:$A$610,"子板塊",明細對照!$B$2:$B$610,$B6) -> 116785.4 | E6: =SUMIFS(明細對照!$F$2:$F$610,明細對照!$A$2:$A$610,"子板塊",明細對照!$B$2:$B$610,$B6) -> 3370.9 | F6: =IF(N(D6)=0,"",E6/D6) -> 0.028864053 | G6: =COUNTIFS(明細對照!$A$2:$A$610,"子板塊",明細對照!$B$2:$B$610,$B6,明細對照!$F$2:$F$610,">0") -> 5 | H6: =COUNTIFS(明細對照!$A$2:$A$610,"子板塊",明細對照!$B$2:$B$610,$B6)-COUNTIFS(明細對照!$A$2:$A$610,"子板塊",明細對照!$B$2:$B$610,$B6,明細對照!$D$2:$D$610,"USD") -> 0 | I6: 0.79 | J6: GM、F、APTV、LEA、MGA
A7: 6 | B7: 煉油與成品油 | C7: 4 | D7: =SUMIFS(明細對照!$E$2:$E$610,明細對照!$A$2:$A$610,"子板塊",明細對照!$B$2:$B$610,$B7) -> 147474 | E7: =SUMIFS(明細對照!$F$2:$F$610,明細對照!$A$2:$A$610,"子板塊",明細對照!$B$2:$B$610,$B7) -> 16455 | F7: =IF(N(D7)=0,"",E7/D7) -> 0.11157899 | G7: =COUNTIFS(明細對照!$A$2:$A$610,"子板塊",明細對照!$B$2:$B$610,$B7,明細對照!$F$2:$F$610,">0") -> 3 | H7: =COUNTIFS(明細對照!$A$2:$A$610,"子板塊",明細對照!$B$2:$B$610,$B7)-COUNTIFS(明細對照!$A$2:$A$610,"子板塊",明細對照!$B$2:$B$610,$B7,明細對照!$D$2:$D$610,"USD") -> 0 | I7: 0.77 | J7: MPC、PSX、VLO、DINO
A8: 7 | B8: 腫瘤與細胞治療 | C8: 8 | D8: =SUMIFS(明細對照!$E$2:$E$610,明細對照!$A$2:$A$610,"子板塊",明細對照!$B$2:$B$610,$B8) -> 743.235 | E8: =SUMIFS(明細對照!$F$2:$F$610,明細對照!$A$2:$A$610,"子板塊",明細對照!$B$2:$B$610,$B8) -> -475.716 | F8: =IF(N(D8)=0,"",E8/D8) -> -0.64006135 | G8: =COUNTIFS(明細對照!$A$2:$A$610,"子板塊",明細對照!$B$2:$B$610,$B8,明細對照!$F$2:$F$610,">0") -> 2 | H8: =COUNTIFS(明細對照!$A$2:$A$610,"子板塊",明細對照!$B$2:$B$610,$B8)-COUNTIFS(明細對照!$A$2:$A$610,"子板塊",明細對照!$B$2:$B$610,$B8,明細對照!$D$2:$D$610,"USD") -> 0 | I8: 0.69 | J8: LEGN、IOVA、ALLO、ARVN、RVMD、NKTX、FATE、CRVS
A9: 8 | B9: 小型模組化核能SMR | C9: 4 | D9: =SUMIFS(明細對照!$E$2:$E$610,明細對照!$A$2:$A$610,"子板塊",明細對照!$B$2:$B$610,$B9) -> 6.622042 | E9: =SUMIFS(明細對照!$F$2:$F$610,明細對照!$A$2:$A$610,"子板塊",明細對照!$B$2:$B$610,$B9) -> -186.80646 | F9: =IF(N(D9)=0,"",E9/D9) -> -28.209797 | G9: =COUNTIFS(明細對照!$A$2:$A$610,"子板塊",明細對照!$B$2:$B$610,$B9,明細對照!$F$2:$F$610,">0") -> 0 | H9: =COUNTIFS(明細對照!$A$2:$A$610,"子板塊",明細對照!$B$2:$B$610,$B9)-COUNTIFS(明細對照!$A$2:$A$610,"子板塊",明細對照!$B$2:$B$610,$B9,明細對照!$D$2:$D$610,"USD") -> 0 | I9: 0.69 | J9: OKLO、SMR、NNE、ASPI
A10: 9 | B10: 電氣設備與電網 | C10: 5 | D10: =SUMIFS(明細對照!$E$2:$E$610,明細對照!$A$2:$A$610,"子板塊",明細對照!$B$2:$B$610,$B10) -> 22372.797 | E10: =SUMIFS(明細對照!$F$2:$F$610,明細對照!$A$2:$A$610,"子板塊",明細對照!$B$2:$B$610,$B10) -> 1693.331 | F10: =IF(N(D10)=0,"",E10/D10) -> 0.07568705 | G10: =COUNTIFS(明細對照!$A$2:$A$610,"子板塊",明細對照!$B$2:$B$610,$B10,明細對照!$F$2:$F$610,">0") -> 3 | H10: =COUNTIFS(明細對照!$A$2:$A$610,"子板塊",明細對照!$B$2:$B$610,$B10)-COUNTIFS(明細對照!$A$2:$A$610,"子板塊",明細對照!$B$2:$B$610,$B10,明細對照!$D$2:$D$610,"USD") -> 0 | I10: 0.66 | J10: ETN、EMR、PWR、HUBB、GEV
A11: 10 | B11: 樓宇產品與HVAC | C11: 5 | D11: =SUMIFS(明細對照!$E$2:$E$610,明細對照!$A$2:$A$610,"子板塊",明細對照!$B$2:$B$610,$B11) -> 21490.776 | E11: =SUMIFS(明細對照!$F$2:$F$610,明細對照!$A$2:$A$610,"子板塊",明細對照!$B$2:$B$610,$B11) -> 3488.032 | F11: =IF(N(D11)=0,"",E11/D11) -> 0.16230368 | G11: =COUNTIFS(明細對照!$A$2:$A$610,"子板塊",明細對照!$B$2:$B$610,$B11,明細對照!$F$2:$F$610,">0") -> 5 | H11: =COUNTIFS(明細對照!$A$2:$A$610,"子板塊",明細對照!$B$2:$B$610,$B11)-COUNTIFS(明細對照!$A$2:$A$610,"子板塊",明細對照!$B$2:$B$610,$B11,明細對照!$D$2:$D$610,"USD") -> 0 | I11: 0.59 | J11: CARR、TT、JCI、LII、AAON
A12: 11 | B12: 電子硬件與EMS/連接器 | C12: 6 | D12: =SUMIFS(明細對照!$E$2:$E$610,明細對照!$A$2:$A$610,"子板塊",明細對照!$B$2:$B$610,$B12) -> 123328 | E12: =SUMIFS(明細對照!$F$2:$F$610,明細對照!$A$2:$A$610,"子板塊",明細對照!$B$2:$B$610,$B12) -> 37224 | F12: =IF(N(D12)=0,"",E12/D12) -> 0.30182927 | G12: =COUNTIFS(明細對照!$A$2:$A$610,"子板塊",明細對照!$B$2:$B$610,$B12,明細對照!$F$2:$F$610,">0") -> 3 | H12: =COUNTIFS(明細對照!$A$2:$A$610,"子板塊",明細對照!$B$2:$B$610,$B12)-COUNTIFS(明細對照!$A$2:$A$610,"子板塊",明細對照!$B$2:$B$610,$B12,明細對照!$D$2:$D$610,"USD") -> 0 | I12: 0.55 | J12: AAPL、DELL、FLEX、JBL、APH、TEL
A13: 12 | B13: 機械與重工 | C13: 5 | D13: =SUMIFS(明細對照!$E$2:$E$610,明細對照!$A$2:$A$610,"子板塊",明細對照!$B$2:$B$610,$B13) -> 58558.7 | E13: =SUMIFS(明細對照!$F$2:$F$610,明細對照!$A$2:$A$610,"子板塊",明細對照!$B$2:$B$610,$B13) -> 10295.2 | F13: =IF(N(D13)=0,"",E13/D13) -> 0.17580991 | G13: =COUNTIFS(明細對照!$A$2:$A$610,"子板塊",明細對照!$B$2:$B$610,$B13,明細對照!$F$2:$F$610,">0") -> 5 | H13: =COUNTIFS(明細對照!$A$2:$A$610,"子板塊",明細對照!$B$2:$B$610,$B13)-COUNTIFS(明細對照!$A$2:$A$610,"子板塊",明細對照!$B$2:$B$610,$B13,明細對照!$D$2:$D$610,"USD") -> 0 | I13: 0.52 | J13: CAT、DE、CMI、PCAR、HON
... A112: 111 | B112: 食品加工 | C112: 4 | D112: =SUMIFS(明細對照!$E$2:$E$610,明細對照!$A$2:$A$610,"子板塊",明細對照!$B$2:$B$610,$B112) -> 16541.006 | E112: =SUMIFS(明細對照!$F$2:$F$610,明細對照!$A$2:$A$610,"子板塊",明細對照!$B$2:$B$610,$B112) -> 2582.156 | F112: =IF(N(D112)=0,"",E112/D112) -> 0.15610635 | G112: =COUNTIFS(明細對照!$A$2:$A$610,"子板塊",明細對照!$B$2:$B$610,$B112,明細對照!$F$2:$F$610,">0") -> 4 | H112: =COUNTIFS(明細對照!$A$2:$A$610,"子板塊",明細對照!$B$2:$B$610,$B112)-COUNTIFS(明細對照!$A$2:$A$610,"子板塊",明細對照!$B$2:$B$610,$B112,明細對照!$D$2:$D$610,"USD") -> 0 | I112: -0.87 | J112: GIS、KHC、HSY、CAG

Sheet AI小群組彙總
A1: # | B1: 群組 | C1: 成分股數 | D1: 營收 Q0 合計 (百萬美元) | E1: 營業利益 Q0 合計 (百萬美元) | F1: 合計營業利益率 % | G1: 盈利成分股數 (營業利益 > 0) | H1: 非美元呈報 (不計入合計) | I1: R5.00 5日資金流向 z | J1: 成分股
A2: 1 | B2: AA1 Neo | C2: 4 | D2: =SUMIFS(明細對照!$E$2:$E$610,明細對照!$A$2:$A$610,"AI 小群組",明細對照!$B$2:$B$610,$B2) -> 3553.274 | E2: =SUMIFS(明細對照!$F$2:$F$610,明細對照!$A$2:$A$610,"AI 小群組",明細對照!$B$2:$B$610,$B2) -> -490.279 | F2: =IF(N(D2)=0,"",E2/D2) -> -0.13797951 | G2: =COUNTIFS(明細對照!$A$2:$A$610,"AI 小群組",明細對照!$B$2:$B$610,$B2,明細對照!$F$2:$F$610,">0") -> 0 | H2: =COUNTIFS(明細對照!$A$2:$A$610,"AI 小群組",明細對照!$B$2:$B$610,$B2)-COUNTIFS(明細對照!$A$2:$A$610,"AI 小群組",明細對照!$B$2:$B$610,$B2,明細對照!$D$2:$D$610,"USD") -> 0 | I2: 0.77 | J2: APLD、IREN、NBIS、CRWV
A3: 2 | B3: C1 HBM | C3: 1 | D3: =SUMIFS(明細對照!$E$2:$E$610,明細對照!$A$2:$A$610,"AI 小群組",明細對照!$B$2:$B$610,$B3) -> 41456 | E3: =SUMIFS(明細對照!$F$2:$F$610,明細對照!$A$2:$A$610,"AI 小群組",明細對照!$B$2:$B$610,$B3) -> 33318 | F3: =IF(N(D3)=0,"",E3/D3) -> 0.80369548 | G3: =COUNTIFS(明細對照!$A$2:$A$610,"AI 小群組",明細對照!$B$2:$B$610,$B3,明細對照!$F$2:$F$610,">0") -> 1 | H3: =COUNTIFS(明細對照!$A$2:$A$610,"AI 小群組",明細對照!$B$2:$B$610,$B3)-COUNTIFS(明細對照!$A$2:$A$610,"AI 小群組",明細對照!$B$2:$B$610,$B3,明細對照!$D$2:$D$610,"USD") -> 0 | I3: 0.69 | J3: MU
A4: 3 | B4: F2 散熱液冷 | C4: 3 | D4: =SUMIFS(明細對照!$E$2:$E$610,明細對照!$A$2:$A$610,"AI 小群組",明細對照!$B$2:$B$610,$B4) -> 8292.965 | E4: =SUMIFS(明細對照!$F$2:$F$610,明細對照!$A$2:$A$610,"AI 小群組",明細對照!$B$2:$B$610,$B4) -> 1485.237 | F4: =IF(N(D4)=0,"",E4/D4) -> 0.17909602 | G4: =COUNTIFS(明細對照!$A$2:$A$610,"AI 小群組",明細對照!$B$2:$B$610,$B4,明細對照!$F$2:$F$610,">0") -> 3 | H4: =COUNTIFS(明細對照!$A$2:$A$610,"AI 小群組",明細對照!$B$2:$B$610,$B4)-COUNTIFS(明細對照!$A$2:$A$610,"AI 小群組",明細對照!$B$2:$B$610,$B4,明細對照!$D$2:$D$610,"USD") -> 0 | I4: 0.65 | J4: TT、MOD、BE
A5: 4 | B5: G1 其他雲平台 | C5: 2 | D5: =SUMIFS(明細對照!$E$2:$E$610,明細對照!$A$2:$A$610,"AI 小群組",明細對照!$B$2:$B$610,$B5) -> 79985 | E5: =SUMIFS(明細對照!$F$2:$F$610,明細對照!$A$2:$A$610,"AI 小群組",明細對照!$B$2:$B$610,$B5) -> 25730 | F5: =IF(N(D5)=0,"",E5/D5) -> 0.32168532 | G5: =COUNTIFS(明細對照!$A$2:$A$610,"AI 小群組",明細對照!$B$2:$B$610,$B5,明細對照!$F$2:$F$610,">0") -> 2 | H5: =COUNTIFS(明細對照!$A$2:$A$610,"AI 小群組",明細對照!$B$2:$B$610,$B5)-COUNTIFS(明細對照!$A$2:$A$610,"AI 小群組",明細對照!$B$2:$B$610,$B5,明細對照!$D$2:$D$610,"USD") -> 0 | I5: 0.61 | J5: META、ORCL
A6: 5 | B6: E1 Server | C6: 3 | D6: =SUMIFS(明細對照!$E$2:$E$610,明細對照!$A$2:$A$610,"AI 小群組",明細對照!$B$2:$B$610,$B6) -> 11119.777 | E6: =SUMIFS(明細對照!$F$2:$F$610,明細對照!$A$2:$A$610,"AI 小群組",明細對照!$B$2:$B$610,$B6) -> 1488.064 | F6: =IF(N(D6)=0,"",E6/D6) -> 0.13382139 | G6: =COUNTIFS(明細對照!$A$2:$A$610,"AI 小群組",明細對照!$B$2:$B$610,$B6,明細對照!$F$2:$F$610,">0") -> 1 | H6: =COUNTIFS(明細對照!$A$2:$A$610,"AI 小群組",明細對照!$B$2:$B$610,$B6)-COUNTIFS(明細對照!$A$2:$A$610,"AI 小群組",明細對照!$B$2:$B$610,$B6,明細對照!$D$2:$D$610,"USD") -> 0 | I6: 0.52 | J6: SMCI、DELL、HPE
A7: 6 | B7: F3 能源 | C7: 10 | D7: =SUMIFS(明細對照!$E$2:$E$610,明細對照!$A$2:$A$610,"AI 小群組",明細對照!$B$2:$B$610,$B7) -> 21040.224 | E7: =SUMIFS(明細對照!$F$2:$F$610,明細對照!$A$2:$A$610,"AI 小群組",明細對照!$B$2:$B$610,$B7) -> 1547.4945 | F7: =IF(N(D7)=0,"",E7/D7) -> 0.073549338 | G7: =COUNTIFS(明細對照!$A$2:$A$610,"AI 小群組",明細對照!$B$2:$B$610,$B7,明細對照!$F$2:$F$610,">0") -> 5 | H7: =COUNTIFS(明細對照!$A$2:$A$610,"AI 小群組",明細對照!$B$2:$B$610,$B7)-COUNTIFS(明細對照!$A$2:$A$610,"AI 小群組",明細對照!$B$2:$B$610,$B7,明細對照!$D$2:$D$610,"USD") -> 1 | I7: 0.5 | J7: OKLO、NNE、LEU、BWXT、SMR、NRG、CEG、VST、TLN、CCJ
A8: 7 | B8: D5 連接器 | C8: 2 | D8: =SUMIFS(明細對照!$E$2:$E$610,明細對照!$A$2:$A$610,"AI 小群組",明細對照!$B$2:$B$610,$B8) -> 5160 | E8: =SUMIFS(明細對照!$F$2:$F$610,明細對照!$A$2:$A$610,"AI 小群組",明細對照!$B$2:$B$610,$B8) -> 1073 | F8: =IF(N(D8)=0,"",E8/D8) -> 0.20794574 | G8: =COUNTIFS(明細對照!$A$2:$A$610,"AI 小群組",明細對照!$B$2:$B$610,$B8,明細對照!$F$2:$F$610,">0") -> 1 | H8: =COUNTIFS(明細對照!$A$2:$A$610,"AI 小群組",明細對照!$B$2:$B$610,$B8)-COUNTIFS(明細對照!$A$2:$A$610,"AI 小群組",明細對照!$B$2:$B$610,$B8,明細對照!$D$2:$D$610,"USD") -> 0 | I8: 0.49 | J8: APH、TEL
A9: 8 | B9: A1 GPU | C9: 3 | D9: =SUMIFS(明細對照!$E$2:$E$610,明細對照!$A$2:$A$610,"AI 小群組",明細對照!$B$2:$B$610,$B9) -> 123885 | E9: =SUMIFS(明細對照!$F$2:$F$610,明細對照!$A$2:$A$610,"AI 小群組",明細對照!$B$2:$B$610,$B9) -> 67690 | F9: =IF(N(D9)=0,"",E9/D9) -> 0.54639383 | G9: =COUNTIFS(明細對照!$A$2:$A$610,"AI 小群組",明細對照!$B$2:$B$610,$B9,明細對照!$F$2:$F$610,">0") -> 3 | H9: =COUNTIFS(明細對照!$A$2:$A$610,"AI 小群組",明細對照!$B$2:$B$610,$B9)-COUNTIFS(明細對照!$A$2:$A$610,"AI 小群組",明細對照!$B$2:$B$610,$B9,明細對照!$D$2:$D$610,"USD") -> 0 | I9: 0.49 | J9: NVDA、AMD、INTC
A10: 9 | B10: F1 電源 | C10: 7 | D10: =SUMIFS(明細對照!$E$2:$E$610,明細對照!$A$2:$A$610,"AI 小群組",明細對照!$B$2:$B$610,$B10) -> 33506.807 | E10: =SUMIFS(明細對照!$F$2:$F$610,明細對照!$A$2:$A$610,"AI 小群組",明細對照!$B$2:$B$610,$B10) -> 3193.064 | F10: =IF(N(D10)=0,"",E10/D10) -> 0.09529598 | G10: =COUNTIFS(明細對照!$A$2:$A$610,"AI 小群組",明細對照!$B$2:$B$610,$B10,明細對照!$F$2:$F$610,">0") -> 5 | H10: =COUNTIFS(明細對照!$A$2:$A$610,"AI 小群組",明細對照!$B$2:$B$610,$B10)-COUNTIFS(明細對照!$A$2:$A$610,"AI 小群組",明細對照!$B$2:$B$610,$B10,明細對照!$D$2:$D$610,"USD") -> 1 | I10: 0.41 | J10: PWR、VRT、ETN、SBGSY、GEV、GNRC、CMI
A11: 10 | B11: D6 光纖 | C11: 1 | D11: =SUMIFS(明細對照!$E$2:$E$610,明細對照!$A$2:$A$610,"AI 小群組",明細對照!$B$2:$B$610,$B11) -> 4505 | E11: =SUMIFS(明細對照!$F$2:$F$610,明細對照!$A$2:$A$610,"AI 小群組",明細對照!$B$2:$B$610,$B11) -> 698 | F11: =IF(N(D11)=0,"",E11/D11) -> 0.15493896 | G11: =COUNTIFS(明細對照!$A$2:$A$610,"AI 小群組",明細對照!$B$2:$B$610,$B11,明細對照!$F$2:$F$610,">0") -> 1 | H11: =COUNTIFS(明細對照!$A$2:$A$610,"AI 小群組",明細對照!$B$2:$B$610,$B11)-COUNTIFS(明細對照!$A$2:$A$610,"AI 小群組",明細對照!$B$2:$B$610,$B11,明細對照!$D$2:$D$610,"USD") -> 0 | I11: 0.28 | J11: GLW
A12: 11 | B12: C2 NAND | C12: 3 | D12: =SUMIFS(明細對照!$E$2:$E$610,明細對照!$A$2:$A$610,"AI 小群組",明細對照!$B$2:$B$610,$B12) -> 16341 | E12: =SUMIFS(明細對照!$F$2:$F$610,明細對照!$A$2:$A$610,"AI 小群組",明細對照!$B$2:$B$610,$B12) -> 10206 | F12: =IF(N(D12)=0,"",E12/D12) -> 0.62456398 | G12: =COUNTIFS(明細對照!$A$2:$A$610,"AI 小群組",明細對照!$B$2:$B$610,$B12,明細對照!$F$2:$F$610,">0") -> 3 | H12: =COUNTIFS(明細對照!$A$2:$A$610,"AI 小群組",明細對照!$B$2:$B$610,$B12)-COUNTIFS(明細對照!$A$2:$A$610,"AI 小群組",明細對照!$B$2:$B$610,$B12,明細對照!$D$2:$D$610,"USD") -> 0 | I12: 0.2 | J12: SNDK、WDC、STX
A13: 12 | B13: B1 Foundry | C13: 2 | D13: =SUMIFS(明細對照!$E$2:$E$610,明細對照!$A$2:$A$610,"AI 小群組",明細對照!$B$2:$B$610,$B13) -> 1786 | E13: =SUMIFS(明細對照!$F$2:$F$610,明細對照!$A$2:$A$610,"AI 小群組",明細對照!$B$2:$B$610,$B13) -> 174 | F13: =IF(N(D13)=0,"",E13/D13) -> 0.097424412 | G13: =COUNTIFS(明細對照!$A$2:$A$610,"AI 小群組",明細對照!$B$2:$B$610,$B13,明細對照!$F$2:$F$610,">0") -> 1 | H13: =COUNTIFS(明細對照!$A$2:$A$610,"AI 小群組",明細對照!$B$2:$B$610,$B13)-COUNTIFS(明細對照!$A$2:$A$610,"AI 小群組",明細對照!$B$2:$B$610,$B13,明細對照!$D$2:$D$610,"USD") -> 1 | I13: 0.2 | J13: TSM、GFS
... A34: 33 | B34: B5 EDA | C34: 2 | D34: =SUMIFS(明細對照!$E$2:$E$610,明細對照!$A$2:$A$610,"AI 小群組",明細對照!$B$2:$B$610,$B34) -> 4061.273 | E34: =SUMIFS(明細對照!$F$2:$F$610,明細對照!$A$2:$A$610,"AI 小群組",明細對照!$B$2:$B$610,$B34) -> 809.618 | F34: =IF(N(D34)=0,"",E34/D34) -> 0.19935079 | G34: =COUNTIFS(明細對照!$A$2:$A$610,"AI 小群組",明細對照!$B$2:$B$610,$B34,明細對照!$F$2:$F$610,">0") -> 2 | H34: =COUNTIFS(明細對照!$A$2:$A$610,"AI 小群組",明細對照!$B$2:$B$610,$B34)-COUNTIFS(明細對照!$A$2:$A$610,"AI 小群組",明細對照!$B$2:$B$610,$B34,明細對照!$D$2:$D$610,"USD") -> 0 | I34: -1.37 | J34: SNPS、CDNS

Sheet 分級彙總
A1: 級 | B1: 定義（營業利益口徑） | C1: 數量 | D1: 佔比 | E1: Tickers
A2: A | B2: 四季營業利益全部為正 —— 持續盈利 | C2: =COUNTIF(觀察名單!$AA$2:$AA$533,$A2) -> 350 | D2: =IF(N($C$7)=0,"",C2/$C$7) -> 0.65789474 | E2: A、AAON、AAPL、ABBV、ACN、ADBE、ADI、ADM、ADP、AEM、AEP、AFL、AFRM、AG、AIG、AJG、ALAB、AMAT、AMD、AMG、AMGN、AMH、AMKR、AMT、ANET、AON、APD、APO、APTV、ARES、ARM、ASML、ASX、ATO、AU、AWK、AWR、BC、BE、BEN、BG、BIDU、BIIB、BJ、BKR、BLK、BMY、BRO、BWXT、BXP、CAG、CAH、CAMT、CARR、CAT、CB、CBOE、CBRE、CCI、CCJ、CCL、CDE、CDNS、CELH、CENX、CF、CHEF、CHTR、CHWY、CI、CIEN、CL、CLH、CMCSA、CME、CMG、CMI、COHR、COP、COR、COST、CRCL、CRDO、CRM、CSCO、CSX、CTAS、CTSH、CVS、CVX、CWST、CWT、DAL、DE、DECK、DHI、DHR、DIS、DOC、DOCS、DRI、DUOL、DVN、EBAY、ECL、EE、EGP、EHC、EL、ELV、EME、EPAM、EPD、EQIX、ET、FANG、FCX、FDX、FN、FR、FRT、FSLR、FTNT、FWONK、GD、GEV、GFS、GILD、GIS、GLNG、GLPI、GLW、GOLD、GOOGL、HAL、HBM、HCA、HCC、HD、HLT、HON、HOOD、HSY、HTO、HUBB、IBM、ICE、INFY、INGR、INTC、INVH、IPGP、ISRG、JBHT、JBL、JCI、JEF、JLL、JNJ、KALU、KDP、KGC、KHC、KIM、KKR、KLAC、KMB、KMI、KO、LAMR、LEA、LEN、LHX、LII、LIN、LITE、LLY、LMT、LOW、LRCX、LRN、LULU、LUV、LVS、MA、MAA、MAN、MAR、MCD、MCK、MDT、MET、META、MGA、MGM、MLM、MNST、MO、MOD、MPC、MPWR、MRVL、MSFT、MTCH、MTSI、MTZ、MU、NCLH、NDAQ、NDSN、NE、NEE、NEM、NFLX、NI、NJR、NKE、NOC、NOW、NRG、NSC、NTR、NUE、NVDA、NVO、NVR、NWSA、NXPI、NXT、O、ODFL、OHI、OKE、ON、ONON、ONTO、ORCL、OWL、OXY、PAAS、PAYX、PCAR、PEP、PFE、PFGC、PG、PGR、PHM、PKG、PLD、PLTR、PM、POOL、PSA、PSX、PWR、PYPL、QCOM、RCL、RDDT、REGN、RGLD、RIG、RL、RMBS、RNR、ROK、ROKU、ROST、RS、RSG、RTX、SBAC、SBUX、SCCO、SCI、SHOP、SHW、SIMO、SLB、SMCI、SMTC、SNDK、SNPS、SO、SPG、SPGI、STAG、STLD、STX、STZ、SYK、SYY、T、TAP、TDW、TECK、TEL、TER、THC、TJX、TMO、TMUS、TOL、TOST、TPB、TROW、TRV、TSEM、TSLA、TSM、TSN、TT、TXN、UAL、UHS、UMC、UNH、UNP、UPS、USFD、V、VAL、VG、VIAV、VICI、VLO、VMC、VNO、VRT、VRTX、VST、VTR、VZ、W、WBD、WCN、WDAY、WDC、WFRD、WHR、WM、WMB、WMT、WTRG、WTW、XEL、XOM、XPO、YUM
A3: B | B3: 最新季營業利益為正，但四季之中有負 —— 剛轉正或有波動 | C3: =COUNTIF(觀察名單!$AA$2:$AA$533,$A3) -> 41 | D3: =IF(N($C$7)=0,"",C3/$C$7) -> 0.077067669 | E3: AA、AAL、ACI、ALB、ARVN、AVAV、AXTI、BABA、CNC、CNR、COMP、CRH、DDOG、DOW、ENPH、F、FLR、GM、GNRC、GPN、HRB、HUM、IP、J、KR、LEGN、LEU、LNC、LNG、LYB、LYV、MDB、OSCR、PLTK、RUN、SLG、SR、SYM、TEAM、TLN、Z
A4: C | B4: 最新季營業利益為負，但較 Q-3 收窄 —— 虧損收窄 | C4: =COUNTIF(觀察名單!$AA$2:$AA$533,$A4) -> 33 | D4: =IF(N($C$7)=0,"",C4/$C$7) -> 0.062030075 | E4: AEHR、ALEC、BEAM、CLF、CRSP、CRWD、DKNG、DNLI、DNN、DTIL、EQH、FATE、FLUT、IONS、IOVA、LASR、LPTH、MDGL、MP、PARA、PL、RBLX、RDW、RIVN、RKLB、RXT、S、SMR、SOUN、TDOC、TTWO、UUUU、ZS
A5: D | B5: 最新季營業利益為負且較 Q-3 擴大（或由正轉負） —— 惡化 | C5: =COUNTIF(觀察名單!$AA$2:$AA$533,$A5) -> 54 | D5: =IF(N($C$7)=0,"",C5/$C$7) -> 0.10150376 | E5: AAOI、ACM、ALLO、ALOY、ALT、AMR、AMS、APLD、ASPI、ASTS、BTU、CEG、COIN、CRVS、CRWV、HIMS、IONQ、IREN、KTOS、LCID、LUNR、LWLG、MARA、METC、MOS、MRK、NB、NBIS、NET、NFE、NKTX、NNE、NTLA、OKLO、ONDS、OPEN、PANW、PINS、POET、PRIM、QBTS、QUBT、RCAT、RGTI、RHI、RIOT、RVMD、SANA、SNAP、TMC、UEC、USAR、VECO、VKTX
A6: — | B6: 四季營業利益唔齊，無法判定 | C6: =COUNTIF(觀察名單!$AA$2:$AA$533,$A6) -> 54 | D6: =IF(N($C$7)=0,"",C6/$C$7) -> 0.10150376 | E6: ABT、AI、AMZN、APH、AVGO、AXP、BA、BAC、BBY、BF.B、BSX、BX、C、CHD、COF、CTVA、D、DELL、DEO、DINO、DLR、DUK、EMR、EOG、ETN、EVR、EXR、FLEX、FORM、GS、HIW、HL、HPE、ILMN、JPM、LAZ、MHK、MS、MTB、NTAP、PNC、PRU、REG、SBGSY、SNOW、SOFI、SYF、TCEHY、TFC、UPST、USB、WELL、WFC、ZION
B7: 合計 | C7: =SUM(C2:C6) -> 532

Sheet 圖表連結
A1: # | B1: 美股 | C1: 公司 | D1: 級 | E1: 純文字 URL
A2: 1 | B2: A | C2: Agilent Technologies, Inc. | D2: =IFERROR(INDEX(觀察名單!$AA$2:$AA$533,MATCH($B2,觀察名單!$B$2:$B$533,0)),"") -> A | E2: https://www.tradingview.com/chart/Q1c5VWwD/?symbol=a
A3: 2 | B3: AA | C3: Alcoa Corporation | D3: =IFERROR(INDEX(觀察名單!$AA$2:$AA$533,MATCH($B3,觀察名單!$B$2:$B$533,0)),"") -> B | E3: https://www.tradingview.com/chart/Q1c5VWwD/?symbol=aa
A4: 3 | B4: AAL | C4: American Airlines Group Inc. | D4: =IFERROR(INDEX(觀察名單!$AA$2:$AA$533,MATCH($B4,觀察名單!$B$2:$B$533,0)),"") -> B | E4: https://www.tradingview.com/chart/Q1c5VWwD/?symbol=aal
A5: 4 | B5: AAOI | C5: Applied Optoelectronics, Inc. | D5: =IFERROR(INDEX(觀察名單!$AA$2:$AA$533,MATCH($B5,觀察名單!$B$2:$B$533,0)),"") -> D | E5: https://www.tradingview.com/chart/Q1c5VWwD/?symbol=aaoi
A6: 5 | B6: AAON | C6: AAON, Inc. | D6: =IFERROR(INDEX(觀察名單!$AA$2:$AA$533,MATCH($B6,觀察名單!$B$2:$B$533,0)),"") -> A | E6: https://www.tradingview.com/chart/Q1c5VWwD/?symbol=aaon
A7: 6 | B7: AAPL | C7: Apple Inc. | D7: =IFERROR(INDEX(觀察名單!$AA$2:$AA$533,MATCH($B7,觀察名單!$B$2:$B$533,0)),"") -> A | E7: https://www.tradingview.com/chart/Q1c5VWwD/?symbol=aapl
A8: 7 | B8: ABBV | C8: AbbVie Inc. | D8: =IFERROR(INDEX(觀察名單!$AA$2:$AA$533,MATCH($B8,觀察名單!$B$2:$B$533,0)),"") -> A | E8: https://www.tradingview.com/chart/Q1c5VWwD/?symbol=abbv
A9: 8 | B9: ABT | C9: Abbott Laboratories | D9: =IFERROR(INDEX(觀察名單!$AA$2:$AA$533,MATCH($B9,觀察名單!$B$2:$B$533,0)),"") -> — | E9: https://www.tradingview.com/chart/Q1c5VWwD/?symbol=abt
A10: 9 | B10: ACI | C10: Albertsons Companies, Inc. | D10: =IFERROR(INDEX(觀察名單!$AA$2:$AA$533,MATCH($B10,觀察名單!$B$2:$B$533,0)),"") -> B | E10: https://www.tradingview.com/chart/Q1c5VWwD/?symbol=aci
A11: 10 | B11: ACM | C11: AECOM | D11: =IFERROR(INDEX(觀察名單!$AA$2:$AA$533,MATCH($B11,觀察名單!$B$2:$B$533,0)),"") -> D | E11: https://www.tradingview.com/chart/Q1c5VWwD/?symbol=acm
A12: 11 | B12: ACN | C12: Accenture plc | D12: =IFERROR(INDEX(觀察名單!$AA$2:$AA$533,MATCH($B12,觀察名單!$B$2:$B$533,0)),"") -> A | E12: https://www.tradingview.com/chart/Q1c5VWwD/?symbol=acn
A13: 12 | B13: ADBE | C13: Adobe Inc. | D13: =IFERROR(INDEX(觀察名單!$AA$2:$AA$533,MATCH($B13,觀察名單!$B$2:$B$533,0)),"") -> A | E13: https://www.tradingview.com/chart/Q1c5VWwD/?symbol=adbe
... A533: 532 | B533: ZS | C533: Zscaler, Inc. | D533: =IFERROR(INDEX(觀察名單!$AA$2:$AA$533,MATCH($B533,觀察名單!$B$2:$B$533,0)),"") -> C | E533: https://www.tradingview.com/chart/Q1c5VWwD/?symbol=zs

Sheet 資料來源
A1: 類別 | B1: 來源 | C1: 用途 | D1: 備註 / 連結
A2: 財報數字 | B2: Yahoo Finance（yfinance income_stmt / quarterly_income_stmt） | C2: 營收、毛利、營業利益、淨利、年度數字 | D2: 由 GitHub Actions runner 拉取（研究容器無法連 Yahoo），檔案 data/yahoo/fundamentals_income.csv
A3: 公司資料 | B3: Yahoo Finance（yfinance info） | C3: 公司名稱、呈報幣別、行業分類 | D3: data/yahoo/fundamentals_profile.csv
A4: 成分股名單 | B4: Sub-Sector 資金流向 Watchlist R4.00 | C4: C 欄子板塊歸屬（491 隻） | D4: 計分視窗至 2026-09-04 收盤；data/subsector_flow4.json
A5: 成分股名單 | B5: AI Sector 資金流向 Watchlist R5.00 | C5: E 欄 AI 小群組歸屬（111 隻） | D5: 計分視窗至 2026-09-04 收盤；data/ai_flow5.json
A6: 圖表 | B6: TradingView | C6: B 欄與「圖表連結」分頁 | D6: 沿用 layout /chart/Q1c5VWwD/
A7: 免責 | B7: — | C7: — | D7: 本表為公開資料整理與研究參考，非投資建議；財務數據以各公司正式公告為準。
